Workbook

Sheet Cómo leer
A1: SEMANA DEL 12 AL 18 DE OCTUBRE
A2: Qué cambió esta semana | B2: Guiones más largos (2 a 3 min en TikTok) y ajustados con los hallazgos de tu competencia: cada pieza trae LISTA DE 3, un DATO real (estudio o famoso) y un HACKEO para hacer contigo.
A3: TÍTULO DEL REEL | B3: Columna E, en morado grande: es el nombre de cada reel. Va como texto grande en pantalla los primeros 3 segundos y como portada.
A4: Guion por tiempos | B4: Todo lo que dices, con el segundo en que va cada parte. Las partes con ✂️ forman el corte de 60 a 90 s para Reels y Shorts.
A5: TU HISTORIA | B5: Va entre [corchetes]: es tu experiencia real, yo no la invento. Llénala antes de grabar o sáltala.
A6: Datos y famosos | B6: Todos son hechos públicos (Stanford 2023, Pennebaker, Skinner, Viktor Frankl, OMS, Gollwitzer, Jim Carrey, Beyoncé, Steve Jobs, Sara Blakely). Se dicen como dato, sin prometer resultados.
A7: Hora (Monterrey) | B7: De tus 40 TikToks: de 18 a 21 h rinden 6.3x tu mediana (7 videos) y de 10 a 13 h, 1.6x (5 videos). Es una señal, no una certeza.
A8: Hashtags | B8: 5 por pieza: #mabradiante + 2 del problema del día + 1 de tu nicho + #mty.
A9: Rendimiento esperado | B9: La meta contra tus propios números. No es una predicción.
A10: Celdas amarillas | B10: Las llenas tú: ¿Grabado?, ¿Publicado?, tus números reales y si coincidió con la simulación.
A11: Pestañas | B11: Calendario · Guion por partes · Mi semana · Podcast y YouTube · Querido Ex · Competencia (79 piezas) · Patrones de viralidad.

Sheet Calendario
A1: Día | B1: Fecha | C1: Hora (Monterrey) | D1: PIEZA | E1: TÍTULO DEL REEL (portada / texto en pantalla) | F1: PLATAFORMAS | G1: TEMA (problema) | H1: TIPO DE HOOK | I1: EMOCIÓN | J1: GUION COMPLETO POR TIEMPOS (✂️ = va en el corte de Reels) | K1: DURACIÓN | L1: FORMATO | M1: CTA: comenta… | N1: Producto | O1: COPY OUT (TikTok, Instagram y Facebook) | P1: Título YouTube Shorts | Q1: HASHTAGS | R1: RENDIMIENTO ESPERADO | S1: PATRÓN viral que usa | T1: Por qué en este orden y a esta hora | U1: Simulación (no predice vistas) | V1: Calificación | W1: Nota de la pieza | X1: ¿Grabado? | Y1: ¿Publicado? | Z1: Vistas reales | AA1: Likes reales | AB1: Comentarios reales | AC1: Compartidos reales | AD1: ¿Coincidió con la simulación?
A2: Lunes | B2: 2026-10-12 | C2: 12:30 | D2: LUN-1 | E2: 3 SEÑALES DE QUE TU MENTE RECHAZA EL DINERO | F2: TikTok · Instagram Reels · Facebook Reels · YouTube Shorts | G2: Dinero · programas de escasez | H2: G1 + lista · Romper creencia + 3 señales | I2: Identificación: «eso me pasa a mí» | J2: [0:00–0:11] GANCHO ✂️: "No es que no te alcance el dinero. Es que tu mente tiene 3 programas que lo sacan de tu vida, y casi nadie los ve." [0:11–0:21] GUARDAR Y COMPARTIR ✂️: "Guarda este video antes de que se te pierda y compártelo con alguien que siente que el dinero se le escapa de las manos." [0:21–0:41] DOLOR: "Te pagan y a la semana ya no hay. Te llega un dinero extra y justo aparece un gasto del mismo tamaño. Y empiezas a creer que el dinero no es para ti. No eres tú. Es un programa que se instaló antes de que pudieras elegirlo." [0:41–1:02] LISTA DE 3 ✂️: "Estas son las 3 señales: 1. Cuando te llega dinero sientes alivio… y luego culpa o miedo a perderlo. 2. Te cuesta cobrar lo que vale tu trabajo, y pedir más te da vergüenza. 3. En tu casa, hablar de dinero era sinónimo de pelea o de «no alcanza»." [1:02–1:25] DATO / AUTORIDAD: "Los investigadores Sendhil Mullainathan y Eldar Shafir lo explican en su libro «Escasez»: cuando la mente vive en carencia, le queda menos espacio para pensar y decidir. No es falta de inteligencia: es una mente ocupada sobreviviendo. Desde lo energético, es una frecuencia de «no alcanza» que se repite hasta que la ves." [1:25–1:45] TU HISTORIA: "[TU HISTORIA REAL, 15–20 s: la frase de dinero que más escuchaste de niña y cómo se repitió en tu vida]" [1:45–2:30] HACKEO (hazlo conmigo) ✂️: "Esta noche toma una hoja. Arriba escribe la frase de dinero que más escuchaste de niña. Abajo escribe su versión nueva. Por ejemplo: «no alcanza» se convierte en «el dinero llega y yo sé sostenerlo». Léela en voz alta 3 veces antes de dormir, durante 7 noches. Repite conmigo: el dinero llega y yo sé sostenerlo. El dinero llega y yo sé sostenerlo. El dinero llega y yo sé sostenerlo." [2:30–2:39] REVELACIÓN: "El dinero no se va porque seas mala con él. Se va porque tu cuerpo todavía no se siente seguro teniéndolo." [2:39–2:44] COMENTA ✂️: "Comenta SEÑALES y dime cuál de las 3 es la tuya." [2:44–2:50] CTA: "Sígueme: esta semana te traigo un hackeo para cada área de tu vida." | K2: TikTok ≈ 2:50 min Reels/Shorts ≈ 1:32 min | L2: Video vertical 9:16, cara a cámara. TikTok: versión completa. Reels y Shorts: corte con las partes ✂️. Pon el TÍTULO DEL REEL como texto grande en pantalla los primeros 3 s y como portada. | M2: SEÑALES | N2: Sin venta (conexión) | O2: ¿El dinero se te escapa apenas llega? 💸 Estas son las 3 señales de que tu mente lo está rechazando. Guarda este video y comenta SEÑALES 👇 #mabradiante #dinero #abundancia #hackeatumente #mty | P2: 3 señales de que tu mente rechaza el dinero #mabradiante #dinero #abundancia #hackeatumente #mty #shorts | Q2: #mabradiante #dinero #abundancia #hackeatumente #mty | R2: Meta: superar tu mediana de TikTok (11,850 vistas). Viral para ti: más de 17,775 (1.5x). Instagram, Facebook y YouTube: s/d, los medimos en la rutina semanal. | S2: P1 + P5 · Romper creencia + lista de señales | T2: Pieza 1 abre el tema del día con una creencia rota + lista de 3 señales (el combo que más rinde según tu competencia). Mediodía: tus TikToks de 10 a 13 h rinden 1.6x tu mediana (5 videos). | U2: Primera frase = gancho (G1, G2, G6 o G9), sin saludo: 2 Quita la culpa antes de enseñar: 1 Un dato de ciencia o un ejemplo real (hallazgo 2): 1 Algo para usar ya (hallazgo 1): 2 Pide guardar/compartir en los primeros 15 s: 1 Pide comentar una palabra: 1 Venta al final en 1 frase (o sin venta): 1 Vocabulario BNQ™, nada de la lista prohibida: 1 Total: 10/10 Lista de 3 (hallazgo 2): sí | V2: 10/10 | W2: Pieza de conexión (sin venta). Aplica H2: romper creencia + lista de 3 señales + estudio real.
A3: Lunes | B3: 2026-10-12 | C3: 18:30 | D3: LUN-2 | E3: DI ESTO CADA VEZ QUE PAGUES ALGO | F3: TikTok · Instagram Reels · Facebook Reels · YouTube Shorts | G3: Dinero · miedo al gastar o recibir | H3: G2 · Promesa práctica («Cuidado con este video…») | I3: Alivio: «algo que puedo hacer ya» | J3: [0:00–0:08] GANCHO ✂️: "Cuidado con este video porque vamos a cambiar la forma en que tu cuerpo recibe y suelta el dinero." [0:08–0:16] GUARDAR Y COMPARTIR ✂️: "Guárdalo antes de que se te pierda y compártelo con la amiga que siempre dice «no me alcanza»." [0:16–0:29] DOLOR: "Abres la app del banco y se te aprieta el estómago. Pagas algo y sientes que pierdes. Eso no es tacañería: es tu sistema nervioso asociando dinero con peligro." [0:29–0:46] LISTA DE 3 ✂️: "Lo vamos a hacer en 3 pasos: 1. Antes de pagar, pon la mano en el pecho y exhala largo. 2. Mira el dinero o la pantalla y di el decreto. 3. Sonríe al pagar, aunque al principio te cueste." [0:46–1:02] DATO / AUTORIDAD: "Tu cerebro aprende por repetición: cada vez que repites una sensación, esa conexión neuronal se fortalece. Por eso este ritual se hace 3 veces y durante 7 días. Lo espiritual lo llama decreto; la neurociencia, neuroplasticidad." [1:02–1:47] HACKEO (hazlo conmigo) ✂️: "Hagámoslo juntas ahora. Mano en el pecho. Inhala… y exhala largo. Ahora repite conmigo: gracias por llegar, te recibo con calma, te dejo ir sabiendo que regresas multiplicado. Otra vez: gracias por llegar, te recibo con calma, te dejo ir sabiendo que regresas multiplicado. Una más: gracias por llegar, te recibo con calma, te dejo ir sabiendo que regresas multiplicado. Tarro de miel, tarro de miel, tarro de miel." [1:47–1:55] REVELACIÓN: "No necesitas más dinero para estar en paz con él. Necesitas paz para que el dinero se quede." [1:55–1:58] COMENTA ✂️: "Cuando lo hagas, comenta HECHO ESTÁ." [1:58–2:01] CTA: "Guárdalo y hazlo 7 días seguidos." | K3: TikTok ≈ 2:01 min Reels/Shorts ≈ 1:21 min | L3: Video vertical 9:16, cara a cámara. TikTok: versión completa. Reels y Shorts: corte con las partes ✂️. Pon el TÍTULO DEL REEL como texto grande en pantalla los primeros 3 s y como portada. | M3: HECHO ESTÁ | N3: Sin venta (conexión) | O3: Di esto cada vez que pagues algo 💛 Un ritual de 30 segundos para que tu cuerpo deje de vivir el dinero como peligro. Guárdalo y comenta HECHO ESTÁ 👇 #mabradiante #dinero #abundancia #hackeatumente #mty | P3: Di esto cada vez que pagues algo #mabradiante #dinero #abundancia #hackeatumente #mty #shorts | Q3: #mabradiante #dinero #abundancia #hackeatumente #mty | R3: Meta: superar tu mediana de TikTok (11,850 vistas). Viral para ti: más de 17,775 (1.5x). Instagram, Facebook y YouTube: s/d, los medimos en la rutina semanal. | S3: P2 · Herramienta para usar ya | T3: Pieza 2 es la herramienta para usar ya: el patrón #1 de tu competencia (26x) y el de tus 4 videos más vistos. Va en tu mejor horario: de 18 a 21 h tus TikToks rinden 6.3x tu mediana (7 videos). | U3: Primera frase = gancho (G1, G2, G6 o G9), sin saludo: 2 Quita la culpa antes de enseñar: 0 Un dato de ciencia o un ejemplo real (hallazgo 2): 1 Algo para usar ya (hallazgo 1): 2 Pide guardar/compartir en los primeros 15 s: 1 Pide comentar una palabra: 1 Venta al final en 1 frase (o sin venta): 1 Vocabulario BNQ™, nada de la lista prohibida: 1 Total: 9/10 Lista de 3 (hallazgo 2): sí | V3: 9/10 | W3: Herramienta para usar ya (H1): mismo formato que tus 4 videos más vistos.
A4: Lunes | B4: 2026-10-12 | C4: 20:30 | D4: LUN-3 | E4: EL CHEQUE DE 10 MILLONES DE JIM CARREY | F4: TikTok · Instagram Reels · Facebook Reels · YouTube Shorts | G4: Dinero · visualizas y no llega | H4: G9 · Ejemplo famoso + lista | I4: Curiosidad: «¿cómo lo hizo?» | J4: [0:00–0:12] GANCHO ✂️: "Jim Carrey se escribió un cheque de 10 millones de dólares cuando todavía no tenía éxito. Y lo que hizo después es lo que casi nadie cuenta." [0:12–0:18] GUARDAR Y COMPARTIR ✂️: "Guárdalo y compártelo con alguien que ya hizo su vision board y sigue esperando." [0:18–0:26] DOLOR: "Tú también has escrito metas, has visualizado, has hecho rituales… y nada. Y empiezas a preguntarte qué te falta." [0:26–0:59] LISTA DE 3 ✂️: "Lo que hizo Carrey tiene 3 partes, y si te falta una, tu visualización se queda en sueño: 1. Una cifra y una fecha concretas: él puso 10 millones y Acción de Gracias de 1995. 2. Sentirlo en el cuerpo, no solo pensarlo: él lo cargaba en la cartera y lo veía cada día. 3. Actuar cada día como la persona que ya lo tiene: él mismo dice que no basta con visualizar y sentarse a esperar." [0:59–1:20] DATO / AUTORIDAD: "Carrey contó en entrevistas que a principios de los 90 se escribió ese cheque «por servicios de actuación prestados». Poco antes de esa fecha supo que le pagarían 10 millones por una película. Lo espiritual lo llama decretar; la psicología lo llama identidad: actúas según quien crees que eres." [1:20–1:40] TU HISTORIA: "[TU HISTORIA REAL, 15–20 s: una meta que se te dio cuando empezaste a actuar como si ya la tuvieras]" [1:40–2:21] HACKEO (hazlo conmigo) ✂️: "Hoy escribe tu propio cheque: tu nombre, una cifra realista para los próximos 12 meses y una fecha. Detrás escribe: ¿qué haría hoy la mujer que ya cobra esto? Y haz una de esas cosas hoy mismo. Repite conmigo: soy la mujer que ya lo recibe. Soy la mujer que ya lo recibe. Soy la mujer que ya lo recibe." [2:21–2:28] REVELACIÓN: "El cheque no trae el dinero. Te cambia a ti, y tú traes el dinero." [2:28–2:33] COMENTA ✂️: "Si quieres que te guíe, comenta ADN y te mando el link." [2:33–2:40] CTA: "En ADN Millonario trabajamos los programas de dinero que heredaste para activar tu frecuencia de abundancia." | K4: TikTok ≈ 2:40 min Reels/Shorts ≈ 1:37 min | L4: Video vertical 9:16, cara a cámara. TikTok: versión completa. Reels y Shorts: corte con las partes ✂️. Pon el TÍTULO DEL REEL como texto grande en pantalla los primeros 3 s y como portada. | M4: ADN | N4: ADN Millonario · $750 | O4: Jim Carrey se escribió un cheque de 10 millones antes de tener éxito 🧾 Te cuento las 3 partes que casi nadie hace. Comenta ADN y te mando el link 👇 #mabradiante #dinero #abundancia #hackeatumente #mty | P4: El cheque de 10 millones de Jim Carrey #mabradiante #dinero #abundancia #hackeatumente #mty #shorts | Q4: #mabradiante #dinero #abundancia #hackeatumente #mty | R4: Meta: superar tu mediana de TikTok (11,850 vistas). Viral para ti: más de 17,775 (1.5x). Instagram, Facebook y YouTube: s/d, los medimos en la rutina semanal. | S4: P7 + P5 · Famoso + lista de 3 | T4: Pieza 3 vende, apoyada en un famoso o estudio real (7.6x) + lista. Va al final del día, cuando ya calentaste el tema. Sigue en tu mejor franja. | U4: Primera frase = gancho (G1, G2, G6 o G9), sin saludo: 2 Quita la culpa antes de enseñar: 0 Un dato de ciencia o un ejemplo real (hallazgo 2): 1 Algo para usar ya (hallazgo 1): 2 Pide guardar/compartir en los primeros 15 s: 1 Pide comentar una palabra: 1 Venta al final en 1 frase (o sin venta): 1 Vocabulario BNQ™, nada de la lista prohibida: 1 Total: 9/10 Lista de 3 (hallazgo 2): sí | V4: 9/10 | W4: Pieza de venta del día (1 de 3). Aplica H2: famoso real + lista de 3.
A5: Martes | B5: 2026-10-13 | C5: 12:30 | D5: MAR-1 | E5: 3 SEÑALES DE ANSIEDAD QUE CREES QUE SON TU PERSONALIDAD | F5: TikTok · Instagram Reels · Facebook Reels · YouTube Shorts | G5: Ansiedad · se confunde con personalidad | H5: G1 + lista · Romper creencia + 3 señales | I5: Identificación: «eso me pasa a mí» | J5: [0:00–0:08] GANCHO ✂️: "No eres intensa ni exagerada. Hay 3 señales de ansiedad que la mayoría confunde con su forma de ser." [0:08–0:13] GUARDAR Y COMPARTIR ✂️: "Guárdalo y compártelo con alguien a quien siempre le dicen «relájate»." [0:13–0:26] DOLOR: "Por fuera estás bien, por dentro vas corriendo. Te dicen «relájate» y te dan ganas de llorar. No es que seas así. Es que tu cuerpo aprendió a vivir en alerta." [0:26–0:41] LISTA DE 3 ✂️: "Estas son las 3 señales: 1. Necesitas tener todo bajo control, y un cambio de planes te desarma. 2. Imaginas la peor versión de todo «para estar preparada». 3. Te cuesta descansar sin sentir culpa." [0:41–1:02] DATO / AUTORIDAD: "La ciencia lo explica así: cuando el cerebro se acostumbra a estar en alerta, la amígdala, tu detector de peligro, se activa con más facilidad, y el cuerpo vive como si algo malo estuviera por pasar. Las tradiciones contemplativas lo llaman una mente que no está en el presente." [1:02–1:22] TU HISTORIA: "[TU HISTORIA REAL, 15–20 s: cómo se veía tu ansiedad con TDAH antes de aprender a dirigir tu mente]" [1:22–2:00] HACKEO (hazlo conmigo) ✂️: "Cuando notes una de estas 3 señales, ponle nombre en voz baja: «esto es mi alarma, no la realidad». Luego pregúntate: ¿qué es lo que sí está pasando ahora mismo? Repite conmigo: esto es mi alarma, no la realidad. Esto es mi alarma, no la realidad. Esto es mi alarma, no la realidad." [2:00–2:06] REVELACIÓN: "Tú no eres ansiosa. Tienes una alarma que nadie te enseñó a apagar." [2:06–2:11] COMENTA ✂️: "Comenta ALARMA y dime cuál de las 3 te pasa más." [2:11–2:14] CTA: "Sígueme para más hackeos para tu mente." | K5: TikTok ≈ 2:14 min Reels/Shorts ≈ 1:11 min | L5: Video vertical 9:16, cara a cámara. TikTok: versión completa. Reels y Shorts: corte con las partes ✂️. Pon el TÍTULO DEL REEL como texto grande en pantalla los primeros 3 s y como portada. | M5: ALARMA | N5: Sin venta (conexión) | O5: ¿Y si no eres «intensa», sino que tu cuerpo vive en alerta? 🚨 3 señales de ansiedad que confundes con tu personalidad. Comenta ALARMA 👇 #mabradiante #ansiedad #calmamental #hackeatumente #mty | P5: 3 señales de ansiedad que confundes con tu personalidad #mabradiante #ansiedad #calmamental #hackeatumente #mty #shorts | Q5: #mabradiante #ansiedad #calmamental #hackeatumente #mty | R5: Meta: superar tu mediana de TikTok (11,850 vistas). Viral para ti: más de 17,775 (1.5x). Instagram, Facebook y YouTube: s/d, los medimos en la rutina semanal. | S5: P1 + P5 · Romper creencia + lista de señales | T5: Pieza 1 abre el tema del día con una creencia rota + lista de 3 señales (el combo que más rinde según tu competencia). Mediodía: tus TikToks de 10 a 13 h rinden 1.6x tu mediana (5 videos). | U5: Primera frase = gancho (G1, G2, G6 o G9), sin saludo: 2 Quita la culpa antes de enseñar: 1 Un dato de ciencia o un ejemplo real (hallazgo 2): 1 Algo para usar ya (hallazgo 1): 2 Pide guardar/compartir en los primeros 15 s: 1 Pide comentar una palabra: 1 Venta al final en 1 frase (o sin venta): 1 Vocabulario BNQ™, nada de la lista prohibida: 1 Total: 10/10 Lista de 3 (hallazgo 2): sí | V5: 10/10 | W5: Sin venta. Sin diagnósticos: si la ansiedad es fuerte o constante, recomendar ayuda profesional.
A6: Martes | B6: 2026-10-13 | C6: 18:30 | D6: MAR-2 | E6: EL SUSPIRO QUE BAJA LA ANSIEDAD EN 1 MINUTO | F6: TikTok · Instagram Reels · Facebook Reels · YouTube Shorts | G6: Ansiedad · ataque en el cuerpo | H6: G2 · Promesa práctica | I6: Alivio: «algo que puedo hacer ya» | J6: [0:00–0:07] GANCHO ✂️: "Haz esto conmigo ahora mismo y siente cómo baja la ansiedad en menos de un minuto." [0:07–0:14] GUARDAR Y COMPARTIR ✂️: "Guárdalo para cuando lo necesites y compártelo con alguien que hoy trae el pecho apretado." [0:14–0:24] DOLOR: "Ese nudo en el pecho, el corazón rápido, la mente que no para. Y todos te dicen «respira»… pero nadie te dice cómo." [0:24–0:37] LISTA DE 3 ✂️: "Se llama suspiro cíclico y son 3 pasos: 1. Inhala por la nariz. 2. Encima, una segunda inhalación cortita, hasta llenarte. 3. Exhala largo y lento por la boca." [0:37–1:00] DATO / AUTORIDAD: "En 2023, un estudio de la Universidad de Stanford, publicado en Cell Reports Medicine, comparó varias técnicas de respiración. Las personas que hicieron este suspiro 5 minutos al día mejoraron más su estado de ánimo que las que hicieron meditación de atención. La exhalación larga le avisa a tu cuerpo que no hay peligro." [1:00–1:36] HACKEO (hazlo conmigo) ✂️: "Hagámoslo juntas. Inhala por la nariz… otra inhalación cortita encima… y exhala largo por la boca. Otra vez: inhala… otra cortita… exhala largo. Una vez más: inhala… cortita… y suelta todo. Ahora repite conmigo: estoy a salvo. Estoy a salvo. Estoy a salvo. Hielo azul, hielo azul, hielo azul." [1:36–1:43] REVELACIÓN: "Tu respiración es el control remoto de tu sistema nervioso, y lo traes contigo a todas partes." [1:43–1:46] COMENTA ✂️: "Si sentiste la diferencia, comenta CALMA." [1:46–1:50] CTA: "Guárdalo y hazlo 5 minutos al día esta semana." | K6: TikTok ≈ 1:50 min Reels/Shorts ≈ 1:06 min | L6: Video vertical 9:16, cara a cámara. TikTok: versión completa. Reels y Shorts: corte con las partes ✂️. Pon el TÍTULO DEL REEL como texto grande en pantalla los primeros 3 s y como portada. | M6: CALMA | N6: Sin venta (conexión) | O6: El suspiro que baja la ansiedad en 1 minuto 🫁 Lo estudió Stanford. Hazlo conmigo, guárdalo y comenta CALMA 👇 #mabradiante #ansiedad #calmamental #hackeatumente #mty | P6: El suspiro que baja la ansiedad en 1 minuto #mabradiante #ansiedad #calmamental #hackeatumente #mty #shorts | Q6: #mabradiante #ansiedad #calmamental #hackeatumente #mty | R6: Meta: superar tu mediana de TikTok (11,850 vistas). Viral para ti: más de 17,775 (1.5x). Instagram, Facebook y YouTube: s/d, los medimos en la rutina semanal. | S6: P2 + P7 · Herramienta + estudio | T6: Pieza 2 es la herramienta para usar ya: el patrón #1 de tu competencia (26x) y el de tus 4 videos más vistos. Va en tu mejor horario: de 18 a 21 h tus TikToks rinden 6.3x tu mediana (7 videos). | U6: Primera frase = gancho (G1, G2, G6 o G9), sin saludo: 2 Quita la culpa antes de enseñar: 0 Un dato de ciencia o un ejemplo real (hallazgo 2): 1 Algo para usar ya (hallazgo 1): 2 Pide guardar/compartir en los primeros 15 s: 1 Pide comentar una palabra: 1 Venta al final en 1 frase (o sin venta): 1 Vocabulario BNQ™, nada de la lista prohibida: 1 Total: 9/10 Lista de 3 (hallazgo 2): sí | V6: 9/10 | W6: Herramienta para usar ya (H1) + estudio real (H2). Sin promesas de curación.
A7: Martes | B7: 2026-10-13 | C7: 20:30 | D7: MAR-3 | E7: 15 MINUTOS DE ESCRITURA QUE CALMAN TU MENTE | F7: TikTok · Instagram Reels · Facebook Reels · YouTube Shorts | G7: Ansiedad · mente que no apaga en la noche | H7: G6 · Autoridad científica + lista | I7: Curiosidad: «¿cómo funciona?» | J7: [0:00–0:10] GANCHO ✂️: "Un psicólogo de Texas descubrió que escribir 15 minutos lo que sientes puede bajar tu carga mental. Y casi nadie lo usa." [0:10–0:16] GUARDAR Y COMPARTIR ✂️: "Guárdalo y compártelo con alguien que se acuesta y su mente se prende." [0:16–0:26] DOLOR: "Te acuestas, apagas la luz… y tu mente empieza a repasar todo lo que dijiste, lo que falta y lo que podría salir mal." [0:26–0:40] LISTA DE 3 ✂️: "Tu mente no suelta por 3 errores muy comunes: 1. Intentas no pensar, y piensas más. 2. Te llevas los pendientes a la cama. 3. Te callas lo que sientes para no molestar." [0:40–1:02] DATO / AUTORIDAD: "James Pennebaker, de la Universidad de Texas, estudió la «escritura expresiva»: personas que escribieron de 15 a 20 minutos sobre lo que sentían, durante unos días, reportaron sentirse mejor que las que escribieron de temas neutros. Desde lo energético: lo que no se expresa se queda dando vueltas en tu campo." [1:02–1:22] TU HISTORIA: "[TU HISTORIA REAL, 15–20 s: qué hacías tú en las noches cuando tu mente no te dejaba dormir]" [1:22–2:06] HACKEO (hazlo conmigo) ✂️: "Hoy, antes de dormir: 10 minutos escribiendo sin parar lo que sientes, no lo que tienes que hacer. No corrijas nada. Cuando termines, cierra la libreta y di: lo solté en el papel, ya no lo cargo en el cuerpo. Repite conmigo: lo solté en el papel, ya no lo cargo en el cuerpo. Lo solté en el papel, ya no lo cargo en el cuerpo." [2:06–2:13] REVELACIÓN: "Lo que no se expresa se queda dando vueltas. Lo que escribes deja de cargarte." [2:13–2:19] COMENTA ✂️: "Si tu mente no te deja dormir, comenta DORMIR y te mando el link." [2:19–2:27] CTA: "En Querida Ansiedad te doy la auditoría mental y los audios para bajarle la velocidad a tu mente." | K7: TikTok ≈ 2:27 min Reels/Shorts ≈ 1:20 min | L7: Video vertical 9:16, cara a cámara. TikTok: versión completa. Reels y Shorts: corte con las partes ✂️. Pon el TÍTULO DEL REEL como texto grande en pantalla los primeros 3 s y como portada. | M7: DORMIR | N7: Querida Ansiedad · $399 | O7: 15 minutos de escritura que calman tu mente ✍️ Lo estudió la Universidad de Texas. Te digo cómo hacerlo hoy. Comenta DORMIR y te mando el link 👇 #mabradiante #ansiedad #calmamental #hackeatumente #mty | P7: 15 minutos de escritura que calman tu mente #mabradiante #ansiedad #calmamental #hackeatumente #mty #shorts | Q7: #mabradiante #ansiedad #calmamental #hackeatumente #mty | R7: Meta: superar tu mediana de TikTok (11,850 vistas). Viral para ti: más de 17,775 (1.5x). Instagram, Facebook y YouTube: s/d, los medimos en la rutina semanal. | S7: P7 + P5 · Estudio + lista de 3 | T7: Pieza 3 vende, apoyada en un famoso o estudio real (7.6x) + lista. Va al final del día, cuando ya calentaste el tema. Sigue en tu mejor franja. | U7: Primera frase = gancho (G1, G2, G6 o G9), sin saludo: 2 Quita la culpa antes de enseñar: 0 Un dato de ciencia o un ejemplo real (hallazgo 2): 1 Algo para usar ya (hallazgo 1): 2 Pide guardar/compartir en los primeros 15 s: 1 Pide comentar una palabra: 1 Venta al final en 1 frase (o sin venta): 1 Vocabulario BNQ™, nada de la lista prohibida: 1 Total: 9/10 Lista de 3 (hallazgo 2): sí | V7: 9/10 | W7: Pieza de venta del día (1 de 3). Sin promesas de salud.
A8: Miércoles | B8: 2026-10-14 | C8: 12:30 | D8: MIÉ-1 | E8: 3 SEÑALES DE QUE NO ES AMOR, ES ENGANCHE | F8: TikTok · Instagram Reels · Facebook Reels · YouTube Shorts | G8: Relaciones · enganche que parece amor | H8: G1 + lista · Romper creencia + 3 señales | I8: Identificación: «eso me pasa a mí» | J8: [0:00–0:08] GANCHO ✂️: "No es que lo ames demasiado. Es que tu cerebro está enganchado, y hay 3 señales que lo delatan." [0:08–0:14] GUARDAR Y COMPARTIR ✂️: "Guárdalo y compártelo con esa amiga que siempre vuelve con la misma persona." [0:14–0:24] DOLOR: "Revisas si se conectó. Ves sus historias aunque te duelan. Te prometes no escribirle… y le escribes. No estás loca. Estás enganchada." [0:24–0:44] LISTA DE 3 ✂️: "Estas son las 3 señales: 1. Te sientes peor cuando lo ves, pero no puedes dejar de buscarlo. 2. Un mensaje suyo te sube al cielo y su silencio te tira al piso. 3. Ya sabes que no te hace bien… y aun así lo justificas." [0:44–1:07] DATO / AUTORIDAD: "El psicólogo B. F. Skinner observó que cuando una recompensa llega a veces sí y a veces no, la conducta se vuelve más difícil de soltar. Es lo mismo que pasa con las máquinas tragamonedas. Por eso una relación intermitente engancha más que una estable. En lo energético, es un cordón que sigue abierto." [1:07–1:27] TU HISTORIA: "[TU HISTORIA REAL, 15–20 s: una relación en la que confundiste intensidad con amor]" [1:27–2:06] HACKEO (hazlo conmigo) ✂️: "Esta semana, cada vez que quieras revisar su perfil, cuenta hasta 10 y di en voz baja: esto es enganche, no amor; mi atención es mía. Repite conmigo: esto es enganche, no amor; mi atención es mía. Esto es enganche, no amor; mi atención es mía. Esto es enganche, no amor; mi atención es mía." [2:06–2:13] REVELACIÓN: "El enganche se siente como amor porque es intenso. El amor sano se siente como paz." [2:13–2:17] COMENTA ✂️: "Comenta ENGANCHE si te pasó o te está pasando." [2:17–2:20] CTA: "Sígueme: estoy preparando algo para ayudarte a soltar." | K8: TikTok ≈ 2:20 min Reels/Shorts ≈ 1:17 min | L8: Video vertical 9:16, cara a cámara. TikTok: versión completa. Reels y Shorts: corte con las partes ✂️. Pon el TÍTULO DEL REEL como texto grande en pantalla los primeros 3 s y como portada. | M8: ENGANCHE | N8: Sin venta (conexión) | O8: ¿Es amor o es enganche? 💔 3 señales que lo delatan (y por qué una relación intermitente engancha más). Comenta ENGANCHE 👇 #mabradiante #relaciones #amorpropio #dependenciaemocional #mty | P8: 3 señales de que no es amor, es enganche #mabradiante #relaciones #amorpropio #dependenciaemocional #mty #shorts | Q8: #mabradiante #relaciones #amorpropio #dependenciaemocional #mty | R8: Meta: superar tu mediana de TikTok (11,850 vistas). Viral para ti: más de 17,775 (1.5x). Instagram, Facebook y YouTube: s/d, los medimos en la rutina semanal. | S8: P1 + P5 + P7 · Creencia + lista + estudio | T8: Pieza 1 abre el tema del día con una creencia rota + lista de 3 señales (el combo que más rinde según tu competencia). Mediodía: tus TikToks de 10 a 13 h rinden 1.6x tu mediana (5 videos). | U8: Primera frase = gancho (G1, G2, G6 o G9), sin saludo: 2 Quita la culpa antes de enseñar: 1 Un dato de ciencia o un ejemplo real (hallazgo 2): 1 Algo para usar ya (hallazgo 1): 2 Pide guardar/compartir en los primeros 15 s: 1 Pide comentar una palabra: 1 Venta al final en 1 frase (o sin venta): 1 Vocabulario BNQ™, nada de la lista prohibida: 1 Total: 10/10 Lista de 3 (hallazgo 2): sí | V8: 10/10 | W8: Sin venta. Siembra el tema de Querido Ex sin venderlo todavía. Relaciones es el tema con más virales (H3).
A9: Miércoles | B9: 2026-10-14 | C9: 18:30 | D9: MIÉ-2 | E9: CORTA EL CORDÓN CON ESTE DECRETO | F9: TikTok · Instagram Reels · Facebook Reels · YouTube Shorts | G9: Relaciones · no puedo dejar de pensarle | H9: G2 · Promesa práctica («Cuidado con este video…») | I9: Alivio: «algo que puedo hacer ya» | J9: [0:00–0:07] GANCHO ✂️: "Cuidado con este video si no puedes dejar de pensar en alguien que ya se fue." [0:07–0:14] GUARDAR Y COMPARTIR ✂️: "Guárdalo para la noche en que más lo necesites y compártelo con quien está soltando a alguien." [0:14–0:24] DOLOR: "Ya terminó, pero sigues sintiéndolo. Piensas en él justo cuando él publica algo. Es como si hubiera un cable que nunca se desconectó." [0:24–0:38] LISTA DE 3 ✂️: "El ritual tiene 3 pasos: 1. Cierra los ojos e imagínalo frente a ti. 2. Observa el cordón de luz que los une. 3. Córtalo con amor, sin rabia, con el decreto." [0:38–0:55] DATO / AUTORIDAD: "En muchas tradiciones espirituales se habla de cordones energéticos: los lazos que quedan después de una relación. No es ciencia, es un ritual, y los rituales le dan al cuerpo un cierre que la mente sola no encuentra." [0:55–1:41] HACKEO (hazlo conmigo) ✂️: "Hagámoslo ahora. Cierra los ojos. Imagínalo frente a ti. Mira el cordón que los une. Ahora, en tu mano aparece una espada de luz. Repite conmigo: te devuelvo lo que es tuyo, recupero lo que es mío. Te devuelvo lo que es tuyo, recupero lo que es mío. Te devuelvo lo que es tuyo, recupero lo que es mío. Espada de luz, espada de luz, espada de luz. Corta. Respira. Hecho está." [1:41–1:45] REVELACIÓN: "Soltar no es olvidarlo. Es dejar de darle tu energía." [1:45–1:47] COMENTA ✂️: "Cuando lo hagas, comenta LIBRE." [1:47–1:49] CTA: "Guárdalo para cuando lo necesites." | K9: TikTok ≈ 1:49 min Reels/Shorts ≈ 1:16 min | L9: Video vertical 9:16, cara a cámara. TikTok: versión completa. Reels y Shorts: corte con las partes ✂️. Pon el TÍTULO DEL REEL como texto grande en pantalla los primeros 3 s y como portada. | M9: LIBRE | N9: Sin venta (conexión) | O9: Corta el cordón con este decreto ✂️✨ Para cuando no puedes dejar de pensar en alguien que ya se fue. Guárdalo y comenta LIBRE 👇 #mabradiante #relaciones #amorpropio #dependenciaemocional #mty | P9: Corta el cordón con este decreto #mabradiante #relaciones #amorpropio #dependenciaemocional #mty #shorts | Q9: #mabradiante #relaciones #amorpropio #dependenciaemocional #mty | R9: Meta: superar tu mediana de TikTok (11,850 vistas). Viral para ti: más de 17,775 (1.5x). Instagram, Facebook y YouTube: s/d, los medimos en la rutina semanal. | S9: P2 · Herramienta para usar ya | T9: Pieza 2 es la herramienta para usar ya: el patrón #1 de tu competencia (26x) y el de tus 4 videos más vistos. Va en tu mejor horario: de 18 a 21 h tus TikToks rinden 6.3x tu mediana (7 videos). | U9: Primera frase = gancho (G1, G2, G6 o G9), sin saludo: 2 Quita la culpa antes de enseñar: 0 Un dato de ciencia o un ejemplo real (hallazgo 2): 1 Algo para usar ya (hallazgo 1): 2 Pide guardar/compartir en los primeros 15 s: 1 Pide comentar una palabra: 1 Venta al final en 1 frase (o sin venta): 1 Vocabulario BNQ™, nada de la lista prohibida: 1 Total: 9/10 Lista de 3 (hallazgo 2): sí | V9: 9/10 | W9: Herramienta para usar ya (H1). Es un adelanto del Día 3 de Querido Ex (siembra, sin venta).
A10: Miércoles | B10: 2026-10-14 | C10: 20:30 | D10: MIÉ-3 | E10: BEYONCÉ TENÍA UN ALTER EGO: SASHA FIERCE | F10: TikTok · Instagram Reels · Facebook Reels · YouTube Shorts | G10: Relaciones · te conformas, ruegas | H10: G9 · Ejemplo famoso + estudio + lista | I10: Inspiración: «yo también puedo» | J10: [0:00–0:12] GANCHO ✂️: "Beyoncé contó que era tímida en el escenario hasta que creó a Sasha Fierce. Y eso tiene todo que ver con por qué te conformas en el amor." [0:12–0:18] GUARDAR Y COMPARTIR ✂️: "Guárdalo y compártelo con la amiga que siempre explica de más lo que necesita." [0:18–0:25] DOLOR: "Sabes lo que mereces, pero cuando estás frente a esa persona te haces chiquita. Ruegas, explicas, esperas." [0:25–0:43] LISTA DE 3 ✂️: "Tu alter ego en el amor hace 3 cosas que tú todavía no: 1. No explica de más lo que necesita. 2. Se va cuando algo no le hace bien, sin pedir permiso. 3. Elige con calma, no con hambre de cariño." [0:43–1:05] DATO / AUTORIDAD: "Hay un estudio de 2017 con niños, en la revista Child Development, que encontró algo curioso: los que se imaginaban como un personaje, por ejemplo Batman, perseveraban más en una tarea aburrida. Le llamaron el «efecto Batman». Tomar distancia de ti misma a través de un personaje te da fuerza." [1:05–1:25] TU HISTORIA: "[TU HISTORIA REAL, 15–20 s: una vez que te hiciste chiquita frente a alguien y qué habría hecho tu versión fuerte]" [1:25–2:03] HACKEO (hazlo conmigo) ✂️: "Ponle nombre a tu versión que ya no ruega. Hoy, antes de responder un mensaje, pregúntate: ¿qué haría ella? Y responde desde ahí. Repite conmigo: yo elijo desde mi valor, no desde mi miedo. Yo elijo desde mi valor, no desde mi miedo. Yo elijo desde mi valor, no desde mi miedo." [2:03–2:10] REVELACIÓN: "No necesitas convertirte en otra persona. Necesitas permiso para ser la versión que ya existe en ti." [2:10–2:16] COMENTA ✂️: "Si quieres crear la tuya, comenta ALTER EGO y te mando el link." [2:16–2:23] CTA: "En Crea y Activa tu Alter Ego te guío paso a paso para instalar esa identidad." | K10: TikTok ≈ 2:23 min Reels/Shorts ≈ 1:20 min | L10: Video vertical 9:16, cara a cámara. TikTok: versión completa. Reels y Shorts: corte con las partes ✂️. Pon el TÍTULO DEL REEL como texto grande en pantalla los primeros 3 s y como portada. | M10: ALTER EGO | N10: Crea y Activa tu Alter Ego · $599 | O10: Beyoncé tenía un alter ego: Sasha Fierce 🔥 ¿Y tú? 3 cosas que haría tu versión fuerte en el amor. Comenta ALTER EGO y te mando el link 👇 #mabradiante #relaciones #amorpropio #dependenciaemocional #mty | P10: Beyoncé tenía un alter ego: Sasha Fierce #mabradiante #relaciones #amorpropio #dependenciaemocional #mty #shorts | Q10: #mabradiante #relaciones #amorpropio #dependenciaemocional #mty | R10: Meta: superar tu mediana de TikTok (11,850 vistas). Viral para ti: más de 17,775 (1.5x). Instagram, Facebook y YouTube: s/d, los medimos en la rutina semanal. | S10: P7 + P5 · Famoso + estudio + lista de 3 | T10: Pieza 3 vende, apoyada en un famoso o estudio real (7.6x) + lista. Va al final del día, cuando ya calentaste el tema. Sigue en tu mejor franja. | U10: Primera frase = gancho (G1, G2, G6 o G9), sin saludo: 2 Quita la culpa antes de enseñar: 0 Un dato de ciencia o un ejemplo real (hallazgo 2): 1 Algo para usar ya (hallazgo 1): 2 Pide guardar/compartir en los primeros 15 s: 1 Pide comentar una palabra: 1 Venta al final en 1 frase (o sin venta): 1 Vocabulario BNQ™, nada de la lista prohibida: 1 Total: 9/10 Lista de 3 (hallazgo 2): sí | V10: 9/10 | W10: Pieza de venta del día (1 de 3). Querido Ex todavía no se vende: Alter Ego cubre Relaciones.
A11: Jueves | B11: 2026-10-15 | C11: 12:30 | D11: JUE-1 | E11: 3 SEÑALES DE QUE ESTÁS DESPERTANDO (Y POR QUÉ DUELE) | F11: TikTok · Instagram Reels · Facebook Reels · YouTube Shorts | G11: Vacío · nada me llena | H11: G1 + lista · Reencuadre + 3 señales | I11: Identificación: «eso me pasa a mí» | J11: [0:00–0:07] GANCHO ✂️: "No es que estés perdida. Puede que estés despertando, y hay 3 señales que lo delatan." [0:07–0:14] GUARDAR Y COMPARTIR ✂️: "Guárdalo y compártelo con alguien que siente que ya no encaja en su propia vida." [0:14–0:26] DOLOR: "Tienes lo que se supone que querías, y aun así sientes un vacío. Nadie a tu alrededor lo entiende, y empiezas a pensar que algo está mal contigo." [0:26–0:38] LISTA DE 3 ✂️: "Estas son las 3 señales: 1. Lo que antes te llenaba ahora te aburre. 2. Ya no aguantas conversaciones vacías. 3. Sientes que «tiene que haber algo más»." [0:38–0:57] DATO / AUTORIDAD: "Viktor Frankl, el psiquiatra que sobrevivió a los campos de concentración, llamó «vacío existencial» a esta sensación, y escribió que el ser humano puede soportar casi cualquier cosa si encuentra un para qué. Las tradiciones espirituales lo llaman la noche oscura del alma." [0:57–1:17] TU HISTORIA: "[TU HISTORIA REAL, 15–20 s: el momento en que sentiste que tu vida ya no te quedaba]" [1:17–1:55] HACKEO (hazlo conmigo) ✂️: "Escribe 3 momentos de tu vida en los que te sentiste viva de verdad. Luego busca qué tienen en común. Ahí está la primera pista de tu para qué. Repite conmigo: mi vacío es espacio para lo nuevo. Mi vacío es espacio para lo nuevo. Mi vacío es espacio para lo nuevo." [1:55–2:02] REVELACIÓN: "El vacío no es el final. Es el espacio donde empieza lo que de verdad eres." [2:02–2:04] COMENTA ✂️: "Si te pasa, comenta DESPERTANDO." [2:04–2:07] CTA: "Sígueme para más hackeos de consciencia." | K11: TikTok ≈ 2:07 min Reels/Shorts ≈ 1:06 min | L11: Video vertical 9:16, cara a cámara. TikTok: versión completa. Reels y Shorts: corte con las partes ✂️. Pon el TÍTULO DEL REEL como texto grande en pantalla los primeros 3 s y como portada. | M11: DESPERTANDO | N11: Sin venta (conexión) | O11: ¿Y si no estás perdida, sino despertando? 🌀 3 señales (y lo que dijo Viktor Frankl sobre ese vacío). Comenta DESPERTANDO 👇 #mabradiante #despertardeconciencia #espiritualidad #salirdelamatrix #mty | P11: 3 señales de que estás despertando #mabradiante #despertardeconciencia #espiritualidad #salirdelamatrix #mty #shorts | Q11: #mabradiante #despertardeconciencia #espiritualidad #salirdelamatrix #mty | R11: Meta: superar tu mediana de TikTok (11,850 vistas). Viral para ti: más de 17,775 (1.5x). Instagram, Facebook y YouTube: s/d, los medimos en la rutina semanal. | S11: P1 + P5 + P7 · Creencia + lista + autor | T11: Pieza 1 abre el tema del día con una creencia rota + lista de 3 señales (el combo que más rinde según tu competencia). Mediodía: tus TikToks de 10 a 13 h rinden 1.6x tu mediana (5 videos). | U11: Primera frase = gancho (G1, G2, G6 o G9), sin saludo: 2 Quita la culpa antes de enseñar: 1 Un dato de ciencia o un ejemplo real (hallazgo 2): 1 Algo para usar ya (hallazgo 1): 2 Pide guardar/compartir en los primeros 15 s: 1 Pide comentar una palabra: 1 Venta al final en 1 frase (o sin venta): 1 Vocabulario BNQ™, nada de la lista prohibida: 1 Total: 10/10 Lista de 3 (hallazgo 2): sí | V11: 10/10 | W11: Sin venta. Si la tristeza es constante o hay ideas de no vivir: Línea de la Vida 800 911 2000.
A12: Jueves | B12: 2026-10-15 | C12: 18:30 | D12: JUE-2 | E12: RITUAL DE 3 MINUTOS PARA VOLVER A TI | F12: TikTok · Instagram Reels · Facebook Reels · YouTube Shorts | G12: Vacío · desconexión de mí | H12: G2 · Promesa práctica («Cuidado con este video…») | I12: Alivio: «algo que puedo hacer ya» | J12: [0:00–0:07] GANCHO ✂️: "Cuidado con este video: este ritual de 3 minutos te devuelve a ti cuando te sientes vacía." [0:07–0:13] GUARDAR Y COMPARTIR ✂️: "Guárdalo para mañana temprano y compártelo con alguien que anda en piloto automático." [0:13–0:23] DOLOR: "Te levantas, agarras el celular, y el día se te va sin que te hayas preguntado ni una vez cómo estás tú." [0:23–0:33] LISTA DE 3 ✂️: "Son 3 pasos: 1. Mano en el corazón y 3 respiraciones lentas. 2. Pregúntate: ¿qué necesito hoy? 3. Di el decreto 3 veces." [0:33–0:48] DATO / AUTORIDAD: "La ciencia llama «interocepción» a tu capacidad de sentir lo que pasa dentro de tu cuerpo, y la investigación la relaciona con regular mejor tus emociones. Lo espiritual lo llama volver a tu centro." [0:48–1:24] HACKEO (hazlo conmigo) ✂️: "Hagámoslo ahora. Mano en el corazón. Respira lento… una… dos… tres. Pregúntate en silencio: ¿qué necesito hoy? Escucha lo primero que llegue. Ahora repite conmigo: estoy aquí, estoy despierta, elijo mi camino. Estoy aquí, estoy despierta, elijo mi camino. Estoy aquí, estoy despierta, elijo mi camino. Hecho está." [1:24–1:31] REVELACIÓN: "No necesitas irte a una montaña para encontrarte. Necesitas 3 minutos en los que no te abandones." [1:31–1:33] COMENTA ✂️: "Cuando lo hagas, comenta PRESENTE." [1:33–1:36] CTA: "Guárdalo y hazlo 7 mañanas seguidas." | K12: TikTok ≈ 1:36 min Reels/Shorts ≈ 1:01 min | L12: Video vertical 9:16, cara a cámara. TikTok: versión completa. Reels y Shorts: corte con las partes ✂️. Pon el TÍTULO DEL REEL como texto grande en pantalla los primeros 3 s y como portada. | M12: PRESENTE | N12: Sin venta (conexión) | O12: Ritual de 3 minutos para volver a ti 🤍 Para los días en que te sientes vacía o en piloto automático. Guárdalo y comenta PRESENTE 👇 #mabradiante #despertardeconciencia #espiritualidad #salirdelamatrix #mty | P12: Ritual de 3 minutos para volver a ti #mabradiante #despertardeconciencia #espiritualidad #salirdelamatrix #mty #shorts | Q12: #mabradiante #despertardeconciencia #espiritualidad #salirdelamatrix #mty | R12: Meta: superar tu mediana de TikTok (11,850 vistas). Viral para ti: más de 17,775 (1.5x). Instagram, Facebook y YouTube: s/d, los medimos en la rutina semanal. | S12: P2 · Herramienta para usar ya | T12: Pieza 2 es la herramienta para usar ya: el patrón #1 de tu competencia (26x) y el de tus 4 videos más vistos. Va en tu mejor horario: de 18 a 21 h tus TikToks rinden 6.3x tu mediana (7 videos). | U12: Primera frase = gancho (G1, G2, G6 o G9), sin saludo: 2 Quita la culpa antes de enseñar: 0 Un dato de ciencia o un ejemplo real (hallazgo 2): 1 Algo para usar ya (hallazgo 1): 2 Pide guardar/compartir en los primeros 15 s: 1 Pide comentar una palabra: 1 Venta al final en 1 frase (o sin venta): 1 Vocabulario BNQ™, nada de la lista prohibida: 1 Total: 9/10 Lista de 3 (hallazgo 2): sí | V12: 9/10 | W12: Herramienta para usar ya (H1).
A13: Jueves | B13: 2026-10-15 | C13: 20:30 | D13: JUE-3 | E13: LO QUE STEVE JOBS DIJO SOBRE UNIR LOS PUNTOS | F13: TikTok · Instagram Reels · Facebook Reels · YouTube Shorts | G13: Vacío · no le encuentro sentido | H13: G9 · Ejemplo famoso + lista | I13: Inspiración: «esto tiene sentido» | J13: [0:00–0:10] GANCHO ✂️: "En 2005, Steve Jobs dijo en la Universidad de Stanford una frase que explica por qué hoy no le encuentras sentido a tu vida." [0:10–0:15] GUARDAR Y COMPARTIR ✂️: "Guárdalo y compártelo con alguien que está en plena crisis de sentido." [0:15–0:26] DOLOR: "Miras tu vida y no entiendes para qué pasó lo que pasó: la ruptura, el trabajo que perdiste, la crisis que te obligó a parar." [0:26–0:48] LISTA DE 3 ✂️: "Jobs dijo que los puntos no se unen mirando hacia adelante, solo hacia atrás. Y hay 3 puntos que quizá ya estás uniendo: 1. La crisis que te obligó a parar. 2. La pregunta que no te deja en paz. 3. Lo que de pronto te encuentra, como este video." [0:48–1:03] DATO / AUTORIDAD: "Fue en su discurso de graduación de Stanford: «no puedes unir los puntos mirando hacia adelante; solo puedes unirlos mirando hacia atrás». Lo espiritual lo llama sincronicidad; la psicología, darle sentido a tu historia." [1:03–1:23] TU HISTORIA: "[TU HISTORIA REAL, 15–20 s: un momento difícil que hoy entiendes que te llevó a donde estás]" [1:23–1:59] HACKEO (hazlo conmigo) ✂️: "Dibuja una línea en una hoja. Pon 5 momentos clave de tu vida, buenos y difíciles. Únelos. Y pregúntate: ¿hacia dónde apuntan? Repite conmigo: nada de lo que viví fue en vano. Nada de lo que viví fue en vano. Nada de lo que viví fue en vano." [1:59–2:04] REVELACIÓN: "Tu vida no está desordenada. Todavía no has visto el dibujo completo." [2:04–2:10] COMENTA ✂️: "Si quieres un mapa para tu despertar, comenta DESPIERTA y te mando el link." [2:10–2:17] CTA: "En DESPIERTA te acompaño en los primeros pasos de tu despertar con un mapa claro." | K13: TikTok ≈ 2:17 min Reels/Shorts ≈ 1:19 min | L13: Video vertical 9:16, cara a cámara. TikTok: versión completa. Reels y Shorts: corte con las partes ✂️. Pon el TÍTULO DEL REEL como texto grande en pantalla los primeros 3 s y como portada. | M13: DESPIERTA | N13: DESPIERTA · $499 | O13: Lo que Steve Jobs dijo sobre unir los puntos 🔗 y por qué hoy no le encuentras sentido a tu vida. Comenta DESPIERTA y te mando el link 👇 #mabradiante #despertardeconciencia #espiritualidad #salirdelamatrix #mty | P13: Lo que Steve Jobs dijo sobre unir los puntos #mabradiante #despertardeconciencia #espiritualidad #salirdelamatrix #mty #shorts | Q13: #mabradiante #despertardeconciencia #espiritualidad #salirdelamatrix #mty | R13: Meta: superar tu mediana de TikTok (11,850 vistas). Viral para ti: más de 17,775 (1.5x). Instagram, Facebook y YouTube: s/d, los medimos en la rutina semanal. | S13: P7 + P5 · Famoso + lista de 3 | T13: Pieza 3 vende, apoyada en un famoso o estudio real (7.6x) + lista. Va al final del día, cuando ya calentaste el tema. Sigue en tu mejor franja. | U13: Primera frase = gancho (G1, G2, G6 o G9), sin saludo: 2 Quita la culpa antes de enseñar: 0 Un dato de ciencia o un ejemplo real (hallazgo 2): 1 Algo para usar ya (hallazgo 1): 2 Pide guardar/compartir en los primeros 15 s: 1 Pide comentar una palabra: 1 Venta al final en 1 frase (o sin venta): 1 Vocabulario BNQ™, nada de la lista prohibida: 1 Total: 9/10 Lista de 3 (hallazgo 2): sí | V13: 9/10 | W13: Pieza de venta del día (1 de 3).
... A22: Domingo | B22: 2026-10-18 | C22: 20:30 | D22: DOM-3 | E22: LLAVE DE LUZ: ABRE TU SEMANA CON ESTE DECRETO | F22: TikTok · Instagram Reels · Facebook Reels · YouTube Shorts | G22: Valor · decreto de inicio de semana | H22: G2 · Promesa práctica («Cuidado con este video…») | I22: Alivio + esperanza | J22: [0:00–0:06] GANCHO ✂️: "Cuidado con este video: este decreto abre tu semana antes de que empiece." [0:06–0:11] GUARDAR Y COMPARTIR ✂️: "Guárdalo y compártelo con alguien que quiere empezar la semana diferente." [0:11–0:18] DOLOR: "El domingo en la noche te llega esa sensación en el estómago: otra semana igual." [0:18–0:28] LISTA DE 3 ✂️: "Son 3 pasos: 1. Escribe 3 intenciones para tu semana. 2. Mano en el pecho y respira lento. 3. Di el decreto 3 veces." [0:28–0:45] DATO / AUTORIDAD: "«Llave de luz» es una de mis palabras gatillo: frases cortas que se repiten 3 veces para anclar una intención. Es un ritual, no ciencia: su fuerza está en la repetición y en la intención con que lo dices." [0:45–1:23] HACKEO (hazlo conmigo) ✂️: "Escribe tus 3 intenciones. Mano en el pecho. Respira lento. Ahora repite conmigo: abro mi semana a lo que sí elijo. Abro mi semana a lo que sí elijo. Abro mi semana a lo que sí elijo. Llave de luz, llave de luz, llave de luz. Hecho está, hecho está, hecho está." [1:23–1:29] REVELACIÓN: "Tu semana no empieza el lunes. Empieza cuando decides cómo la vas a vivir." [1:29–1:32] COMENTA ✂️: "Cuando lo hagas, comenta HECHO ESTÁ." [1:32–1:34] CTA: "Guárdalo y hazlo cada domingo." | K22: TikTok ≈ 1:34 min Reels/Shorts ≈ 1:02 min | L22: Video vertical 9:16, cara a cámara. TikTok: versión completa. Reels y Shorts: corte con las partes ✂️. Pon el TÍTULO DEL REEL como texto grande en pantalla los primeros 3 s y como portada. | M22: HECHO ESTÁ | N22: Sin venta (conexión) | O22: Llave de luz 🗝️✨ Abre tu semana con este decreto antes de que empiece. Guárdalo y comenta HECHO ESTÁ 👇 #mabradiante #hackeatumente #espiritualidad #decreto #mty | P22: Llave de luz: abre tu semana con este decreto #mabradiante #hackeatumente #espiritualidad #decreto #mty #shorts | Q22: #mabradiante #hackeatumente #espiritualidad #decreto #mty | R22: Meta: superar tu mediana de TikTok (11,850 vistas). Viral para ti: más de 17,775 (1.5x). Instagram, Facebook y YouTube: s/d, los medimos en la rutina semanal. | S22: P2 · Herramienta para usar ya | T22: Pieza 3 vende, apoyada en un famoso o estudio real (7.6x) + lista. Va al final del día, cuando ya calentaste el tema. Sigue en tu mejor franja. | U22: Primera frase = gancho (G1, G2, G6 o G9), sin saludo: 2 Quita la culpa antes de enseñar: 0 Un dato de ciencia o un ejemplo real (hallazgo 2): 1 Algo para usar ya (hallazgo 1): 2 Pide guardar/compartir en los primeros 15 s: 1 Pide comentar una palabra: 1 Venta al final en 1 frase (o sin venta): 1 Vocabulario BNQ™, nada de la lista prohibida: 1 Total: 9/10 Lista de 3 (hallazgo 2): sí | V22: 9/10 | W22: Sin venta. Mismo formato que tu video viral de 2.2M (decreto + «hecho está»).
W24: Grabadas: | X24: =COUNTIF(X2:X22,"Sí")&" de "&COUNTA(D2:D22)
W25: Publicadas: | X25: =COUNTIF(Y2:Y22,"Sí")&" de "&COUNTA(D2:D22)

Sheet Guion por partes
A1: PIEZA | B1: TÍTULO DEL REEL | C1: GANCHO | D1: GUARDAR Y COMPARTIR | E1: DOLOR | F1: LISTA DE 3 | G1: DATO / AUTORIDAD | H1: TU HISTORIA (real) | I1: HACKEO | J1: REVELACIÓN | K1: COMENTA | L1: CTA
A2: LUN-1 | B2: 3 SEÑALES DE QUE TU MENTE RECHAZA EL DINERO | C2: No es que no te alcance el dinero. Es que tu mente tiene 3 programas que lo sacan de tu vida, y casi nadie los ve. | D2: Guarda este video antes de que se te pierda y compártelo con alguien que siente que el dinero se le escapa de las manos. | E2: Te pagan y a la semana ya no hay. Te llega un dinero extra y justo aparece un gasto del mismo tamaño. Y empiezas a creer que el dinero no es para ti. No eres tú. Es un programa que se instaló antes de que pudieras elegirlo. | F2: Estas son las 3 señales: 1. Cuando te llega dinero sientes alivio… y luego culpa o miedo a perderlo. 2. Te cuesta cobrar lo que vale tu trabajo, y pedir más te da vergüenza. 3. En tu casa, hablar de dinero era sinónimo de pelea o de «no alcanza». | G2: Los investigadores Sendhil Mullainathan y Eldar Shafir lo explican en su libro «Escasez»: cuando la mente vive en carencia, le queda menos espacio para pensar y decidir. No es falta de inteligencia: es una mente ocupada sobreviviendo. Desde lo energético, es una frecuencia de «no alcanza» que se repite hasta que la ves. | H2: [TU HISTORIA REAL, 15–20 s: la frase de dinero que más escuchaste de niña y cómo se repitió en tu vida] | I2: Esta noche toma una hoja. Arriba escribe la frase de dinero que más escuchaste de niña. Abajo escribe su versión nueva. Por ejemplo: «no alcanza» se convierte en «el dinero llega y yo sé sostenerlo». Léela en voz alta 3 veces antes de dormir, durante 7 noches. Repite conmigo: el dinero llega y yo sé sostenerlo. El dinero llega y yo sé sostenerlo. El dinero llega y yo sé sostenerlo. | J2: El dinero no se va porque seas mala con él. Se va porque tu cuerpo todavía no se siente seguro teniéndolo. | K2: Comenta SEÑALES y dime cuál de las 3 es la tuya. | L2: Sígueme: esta semana te traigo un hackeo para cada área de tu vida.
A3: LUN-2 | B3: DI ESTO CADA VEZ QUE PAGUES ALGO | C3: Cuidado con este video porque vamos a cambiar la forma en que tu cuerpo recibe y suelta el dinero. | D3: Guárdalo antes de que se te pierda y compártelo con la amiga que siempre dice «no me alcanza». | E3: Abres la app del banco y se te aprieta el estómago. Pagas algo y sientes que pierdes. Eso no es tacañería: es tu sistema nervioso asociando dinero con peligro. | F3: Lo vamos a hacer en 3 pasos: 1. Antes de pagar, pon la mano en el pecho y exhala largo. 2. Mira el dinero o la pantalla y di el decreto. 3. Sonríe al pagar, aunque al principio te cueste. | G3: Tu cerebro aprende por repetición: cada vez que repites una sensación, esa conexión neuronal se fortalece. Por eso este ritual se hace 3 veces y durante 7 días. Lo espiritual lo llama decreto; la neurociencia, neuroplasticidad. | H3: — | I3: Hagámoslo juntas ahora. Mano en el pecho. Inhala… y exhala largo. Ahora repite conmigo: gracias por llegar, te recibo con calma, te dejo ir sabiendo que regresas multiplicado. Otra vez: gracias por llegar, te recibo con calma, te dejo ir sabiendo que regresas multiplicado. Una más: gracias por llegar, te recibo con calma, te dejo ir sabiendo que regresas multiplicado. Tarro de miel, tarro de miel, tarro de miel. | J3: No necesitas más dinero para estar en paz con él. Necesitas paz para que el dinero se quede. | K3: Cuando lo hagas, comenta HECHO ESTÁ. | L3: Guárdalo y hazlo 7 días seguidos.
A4: LUN-3 | B4: EL CHEQUE DE 10 MILLONES DE JIM CARREY | C4: Jim Carrey se escribió un cheque de 10 millones de dólares cuando todavía no tenía éxito. Y lo que hizo después es lo que casi nadie cuenta. | D4: Guárdalo y compártelo con alguien que ya hizo su vision board y sigue esperando. | E4: Tú también has escrito metas, has visualizado, has hecho rituales… y nada. Y empiezas a preguntarte qué te falta. | F4: Lo que hizo Carrey tiene 3 partes, y si te falta una, tu visualización se queda en sueño: 1. Una cifra y una fecha concretas: él puso 10 millones y Acción de Gracias de 1995. 2. Sentirlo en el cuerpo, no solo pensarlo: él lo cargaba en la cartera y lo veía cada día. 3. Actuar cada día como la persona que ya lo tiene: él mismo dice que no basta con visualizar y sentarse a esperar. | G4: Carrey contó en entrevistas que a principios de los 90 se escribió ese cheque «por servicios de actuación prestados». Poco antes de esa fecha supo que le pagarían 10 millones por una película. Lo espiritual lo llama decretar; la psicología lo llama identidad: actúas según quien crees que eres. | H4: [TU HISTORIA REAL, 15–20 s: una meta que se te dio cuando empezaste a actuar como si ya la tuvieras] | I4: Hoy escribe tu propio cheque: tu nombre, una cifra realista para los próximos 12 meses y una fecha. Detrás escribe: ¿qué haría hoy la mujer que ya cobra esto? Y haz una de esas cosas hoy mismo. Repite conmigo: soy la mujer que ya lo recibe. Soy la mujer que ya lo recibe. Soy la mujer que ya lo recibe. | J4: El cheque no trae el dinero. Te cambia a ti, y tú traes el dinero. | K4: Si quieres que te guíe, comenta ADN y te mando el link. | L4: En ADN Millonario trabajamos los programas de dinero que heredaste para activar tu frecuencia de abundancia.
A5: MAR-1 | B5: 3 SEÑALES DE ANSIEDAD QUE CREES QUE SON TU PERSONALIDAD | C5: No eres intensa ni exagerada. Hay 3 señales de ansiedad que la mayoría confunde con su forma de ser. | D5: Guárdalo y compártelo con alguien a quien siempre le dicen «relájate». | E5: Por fuera estás bien, por dentro vas corriendo. Te dicen «relájate» y te dan ganas de llorar. No es que seas así. Es que tu cuerpo aprendió a vivir en alerta. | F5: Estas son las 3 señales: 1. Necesitas tener todo bajo control, y un cambio de planes te desarma. 2. Imaginas la peor versión de todo «para estar preparada». 3. Te cuesta descansar sin sentir culpa. | G5: La ciencia lo explica así: cuando el cerebro se acostumbra a estar en alerta, la amígdala, tu detector de peligro, se activa con más facilidad, y el cuerpo vive como si algo malo estuviera por pasar. Las tradiciones contemplativas lo llaman una mente que no está en el presente. | H5: [TU HISTORIA REAL, 15–20 s: cómo se veía tu ansiedad con TDAH antes de aprender a dirigir tu mente] | I5: Cuando notes una de estas 3 señales, ponle nombre en voz baja: «esto es mi alarma, no la realidad». Luego pregúntate: ¿qué es lo que sí está pasando ahora mismo? Repite conmigo: esto es mi alarma, no la realidad. Esto es mi alarma, no la realidad. Esto es mi alarma, no la realidad. | J5: Tú no eres ansiosa. Tienes una alarma que nadie te enseñó a apagar. | K5: Comenta ALARMA y dime cuál de las 3 te pasa más. | L5: Sígueme para más hackeos para tu mente.
A6: MAR-2 | B6: EL SUSPIRO QUE BAJA LA ANSIEDAD EN 1 MINUTO | C6: Haz esto conmigo ahora mismo y siente cómo baja la ansiedad en menos de un minuto. | D6: Guárdalo para cuando lo necesites y compártelo con alguien que hoy trae el pecho apretado. | E6: Ese nudo en el pecho, el corazón rápido, la mente que no para. Y todos te dicen «respira»… pero nadie te dice cómo. | F6: Se llama suspiro cíclico y son 3 pasos: 1. Inhala por la nariz. 2. Encima, una segunda inhalación cortita, hasta llenarte. 3. Exhala largo y lento por la boca. | G6: En 2023, un estudio de la Universidad de Stanford, publicado en Cell Reports Medicine, comparó varias técnicas de respiración. Las personas que hicieron este suspiro 5 minutos al día mejoraron más su estado de ánimo que las que hicieron meditación de atención. La exhalación larga le avisa a tu cuerpo que no hay peligro. | H6: — | I6: Hagámoslo juntas. Inhala por la nariz… otra inhalación cortita encima… y exhala largo por la boca. Otra vez: inhala… otra cortita… exhala largo. Una vez más: inhala… cortita… y suelta todo. Ahora repite conmigo: estoy a salvo. Estoy a salvo. Estoy a salvo. Hielo azul, hielo azul, hielo azul. | J6: Tu respiración es el control remoto de tu sistema nervioso, y lo traes contigo a todas partes. | K6: Si sentiste la diferencia, comenta CALMA. | L6: Guárdalo y hazlo 5 minutos al día esta semana.
A7: MAR-3 | B7: 15 MINUTOS DE ESCRITURA QUE CALMAN TU MENTE | C7: Un psicólogo de Texas descubrió que escribir 15 minutos lo que sientes puede bajar tu carga mental. Y casi nadie lo usa. | D7: Guárdalo y compártelo con alguien que se acuesta y su mente se prende. | E7: Te acuestas, apagas la luz… y tu mente empieza a repasar todo lo que dijiste, lo que falta y lo que podría salir mal. | F7: Tu mente no suelta por 3 errores muy comunes: 1. Intentas no pensar, y piensas más. 2. Te llevas los pendientes a la cama. 3. Te callas lo que sientes para no molestar. | G7: James Pennebaker, de la Universidad de Texas, estudió la «escritura expresiva»: personas que escribieron de 15 a 20 minutos sobre lo que sentían, durante unos días, reportaron sentirse mejor que las que escribieron de temas neutros. Desde lo energético: lo que no se expresa se queda dando vueltas en tu campo. | H7: [TU HISTORIA REAL, 15–20 s: qué hacías tú en las noches cuando tu mente no te dejaba dormir] | I7: Hoy, antes de dormir: 10 minutos escribiendo sin parar lo que sientes, no lo que tienes que hacer. No corrijas nada. Cuando termines, cierra la libreta y di: lo solté en el papel, ya no lo cargo en el cuerpo. Repite conmigo: lo solté en el papel, ya no lo cargo en el cuerpo. Lo solté en el papel, ya no lo cargo en el cuerpo. | J7: Lo que no se expresa se queda dando vueltas. Lo que escribes deja de cargarte. | K7: Si tu mente no te deja dormir, comenta DORMIR y te mando el link. | L7: En Querida Ansiedad te doy la auditoría mental y los audios para bajarle la velocidad a tu mente.
A8: MIÉ-1 | B8: 3 SEÑALES DE QUE NO ES AMOR, ES ENGANCHE | C8: No es que lo ames demasiado. Es que tu cerebro está enganchado, y hay 3 señales que lo delatan. | D8: Guárdalo y compártelo con esa amiga que siempre vuelve con la misma persona. | E8: Revisas si se conectó. Ves sus historias aunque te duelan. Te prometes no escribirle… y le escribes. No estás loca. Estás enganchada. | F8: Estas son las 3 señales: 1. Te sientes peor cuando lo ves, pero no puedes dejar de buscarlo. 2. Un mensaje suyo te sube al cielo y su silencio te tira al piso. 3. Ya sabes que no te hace bien… y aun así lo justificas. | G8: El psicólogo B. F. Skinner observó que cuando una recompensa llega a veces sí y a veces no, la conducta se vuelve más difícil de soltar. Es lo mismo que pasa con las máquinas tragamonedas. Por eso una relación intermitente engancha más que una estable. En lo energético, es un cordón que sigue abierto. | H8: [TU HISTORIA REAL, 15–20 s: una relación en la que confundiste intensidad con amor] | I8: Esta semana, cada vez que quieras revisar su perfil, cuenta hasta 10 y di en voz baja: esto es enganche, no amor; mi atención es mía. Repite conmigo: esto es enganche, no amor; mi atención es mía. Esto es enganche, no amor; mi atención es mía. Esto es enganche, no amor; mi atención es mía. | J8: El enganche se siente como amor porque es intenso. El amor sano se siente como paz. | K8: Comenta ENGANCHE si te pasó o te está pasando. | L8: Sígueme: estoy preparando algo para ayudarte a soltar.
A9: MIÉ-2 | B9: CORTA EL CORDÓN CON ESTE DECRETO | C9: Cuidado con este video si no puedes dejar de pensar en alguien que ya se fue. | D9: Guárdalo para la noche en que más lo necesites y compártelo con quien está soltando a alguien. | E9: Ya terminó, pero sigues sintiéndolo. Piensas en él justo cuando él publica algo. Es como si hubiera un cable que nunca se desconectó. | F9: El ritual tiene 3 pasos: 1. Cierra los ojos e imagínalo frente a ti. 2. Observa el cordón de luz que los une. 3. Córtalo con amor, sin rabia, con el decreto. | G9: En muchas tradiciones espirituales se habla de cordones energéticos: los lazos que quedan después de una relación. No es ciencia, es un ritual, y los rituales le dan al cuerpo un cierre que la mente sola no encuentra. | H9: — | I9: Hagámoslo ahora. Cierra los ojos. Imagínalo frente a ti. Mira el cordón que los une. Ahora, en tu mano aparece una espada de luz. Repite conmigo: te devuelvo lo que es tuyo, recupero lo que es mío. Te devuelvo lo que es tuyo, recupero lo que es mío. Te devuelvo lo que es tuyo, recupero lo que es mío. Espada de luz, espada de luz, espada de luz. Corta. Respira. Hecho está. | J9: Soltar no es olvidarlo. Es dejar de darle tu energía. | K9: Cuando lo hagas, comenta LIBRE. | L9: Guárdalo para cuando lo necesites.
A10: MIÉ-3 | B10: BEYONCÉ TENÍA UN ALTER EGO: SASHA FIERCE | C10: Beyoncé contó que era tímida en el escenario hasta que creó a Sasha Fierce. Y eso tiene todo que ver con por qué te conformas en el amor. | D10: Guárdalo y compártelo con la amiga que siempre explica de más lo que necesita. | E10: Sabes lo que mereces, pero cuando estás frente a esa persona te haces chiquita. Ruegas, explicas, esperas. | F10: Tu alter ego en el amor hace 3 cosas que tú todavía no: 1. No explica de más lo que necesita. 2. Se va cuando algo no le hace bien, sin pedir permiso. 3. Elige con calma, no con hambre de cariño. | G10: Hay un estudio de 2017 con niños, en la revista Child Development, que encontró algo curioso: los que se imaginaban como un personaje, por ejemplo Batman, perseveraban más en una tarea aburrida. Le llamaron el «efecto Batman». Tomar distancia de ti misma a través de un personaje te da fuerza. | H10: [TU HISTORIA REAL, 15–20 s: una vez que te hiciste chiquita frente a alguien y qué habría hecho tu versión fuerte] | I10: Ponle nombre a tu versión que ya no ruega. Hoy, antes de responder un mensaje, pregúntate: ¿qué haría ella? Y responde desde ahí. Repite conmigo: yo elijo desde mi valor, no desde mi miedo. Yo elijo desde mi valor, no desde mi miedo. Yo elijo desde mi valor, no desde mi miedo. | J10: No necesitas convertirte en otra persona. Necesitas permiso para ser la versión que ya existe en ti. | K10: Si quieres crear la tuya, comenta ALTER EGO y te mando el link. | L10: En Crea y Activa tu Alter Ego te guío paso a paso para instalar esa identidad.
A11: JUE-1 | B11: 3 SEÑALES DE QUE ESTÁS DESPERTANDO (Y POR QUÉ DUELE) | C11: No es que estés perdida. Puede que estés despertando, y hay 3 señales que lo delatan. | D11: Guárdalo y compártelo con alguien que siente que ya no encaja en su propia vida. | E11: Tienes lo que se supone que querías, y aun así sientes un vacío. Nadie a tu alrededor lo entiende, y empiezas a pensar que algo está mal contigo. | F11: Estas son las 3 señales: 1. Lo que antes te llenaba ahora te aburre. 2. Ya no aguantas conversaciones vacías. 3. Sientes que «tiene que haber algo más». | G11: Viktor Frankl, el psiquiatra que sobrevivió a los campos de concentración, llamó «vacío existencial» a esta sensación, y escribió que el ser humano puede soportar casi cualquier cosa si encuentra un para qué. Las tradiciones espirituales lo llaman la noche oscura del alma. | H11: [TU HISTORIA REAL, 15–20 s: el momento en que sentiste que tu vida ya no te quedaba] | I11: Escribe 3 momentos de tu vida en los que te sentiste viva de verdad. Luego busca qué tienen en común. Ahí está la primera pista de tu para qué. Repite conmigo: mi vacío es espacio para lo nuevo. Mi vacío es espacio para lo nuevo. Mi vacío es espacio para lo nuevo. | J11: El vacío no es el final. Es el espacio donde empieza lo que de verdad eres. | K11: Si te pasa, comenta DESPERTANDO. | L11: Sígueme para más hackeos de consciencia.
A12: JUE-2 | B12: RITUAL DE 3 MINUTOS PARA VOLVER A TI | C12: Cuidado con este video: este ritual de 3 minutos te devuelve a ti cuando te sientes vacía. | D12: Guárdalo para mañana temprano y compártelo con alguien que anda en piloto automático. | E12: Te levantas, agarras el celular, y el día se te va sin que te hayas preguntado ni una vez cómo estás tú. | F12: Son 3 pasos: 1. Mano en el corazón y 3 respiraciones lentas. 2. Pregúntate: ¿qué necesito hoy? 3. Di el decreto 3 veces. | G12: La ciencia llama «interocepción» a tu capacidad de sentir lo que pasa dentro de tu cuerpo, y la investigación la relaciona con regular mejor tus emociones. Lo espiritual lo llama volver a tu centro. | H12: — | I12: Hagámoslo ahora. Mano en el corazón. Respira lento… una… dos… tres. Pregúntate en silencio: ¿qué necesito hoy? Escucha lo primero que llegue. Ahora repite conmigo: estoy aquí, estoy despierta, elijo mi camino. Estoy aquí, estoy despierta, elijo mi camino. Estoy aquí, estoy despierta, elijo mi camino. Hecho está. | J12: No necesitas irte a una montaña para encontrarte. Necesitas 3 minutos en los que no te abandones. | K12: Cuando lo hagas, comenta PRESENTE. | L12: Guárdalo y hazlo 7 mañanas seguidas.
... A22: DOM-3 | B22: LLAVE DE LUZ: ABRE TU SEMANA CON ESTE DECRETO | C22: Cuidado con este video: este decreto abre tu semana antes de que empiece. | D22: Guárdalo y compártelo con alguien que quiere empezar la semana diferente. | E22: El domingo en la noche te llega esa sensación en el estómago: otra semana igual. | F22: Son 3 pasos: 1. Escribe 3 intenciones para tu semana. 2. Mano en el pecho y respira lento. 3. Di el decreto 3 veces. | G22: «Llave de luz» es una de mis palabras gatillo: frases cortas que se repiten 3 veces para anclar una intención. Es un ritual, no ciencia: su fuerza está en la repetición y en la intención con que lo dices. | H22: — | I22: Escribe tus 3 intenciones. Mano en el pecho. Respira lento. Ahora repite conmigo: abro mi semana a lo que sí elijo. Abro mi semana a lo que sí elijo. Abro mi semana a lo que sí elijo. Llave de luz, llave de luz, llave de luz. Hecho está, hecho está, hecho está. | J22: Tu semana no empieza el lunes. Empieza cuando decides cómo la vas a vivir. | K22: Cuando lo hagas, comenta HECHO ESTÁ. | L22: Guárdalo y hazlo cada domingo.

Sheet Mi semana
A1: Día | B1: Tu tarea | C1: Tiempo aprox. | D1: ¿Hecho?
A2: Domingo 11 (tarde-noche) | B2: Grabar las 6 piezas de lunes y martes (LUN-1 a MAR-3). Llena antes los [corchetes] de TU HISTORIA. | C2: 2 h
A3: Lunes 12 | B3: Grabar las 6 piezas de miércoles y jueves (MIÉ-1 a JUE-3). Publicar LUN-1, 2 y 3 a su hora. | C3: 2 h
A4: Martes 13 | B4: Grabar las 9 piezas de viernes, sábado y domingo + el YouTube largo. Publicar MAR-1, 2 y 3. | C4: 3 h
A5: Miércoles 14 a sábado 17 | B5: Publicar a su hora y responder los comentarios con la palabra clave (con el link si es pieza de venta). | C5: 30 min al día
A6: Si aún no grabaste Querido Ex | B6: Miércoles 14: audios 0 al 3. Jueves 15: audios 4 al 7 (pestaña Querido Ex). | C6: 45 min c/u
A7: Domingo 18 (noche) | B7: Me pides tu "rutina semanal". | C7: 15 min
B10: TIPS PARA GRABAR
B11: Ahora los videos duran 2 a 3 minutos en TikTok. Graba la versión completa; del mismo video se corta la versión de Reels con las partes ✂️.
B12: El TÍTULO DEL REEL va como texto grande en pantalla los primeros 3 segundos (así lo hacen las cuentas que más crecen) y como portada.
B13: En el HACKEO, haz el ejercicio de verdad mientras lo dices: que te vean hacerlo.
B14: Los [corchetes] de TU HISTORIA son para tu experiencia real. Si no tienes una, sáltate esa parte.

Sheet Podcast y YouTube
A1: Día | B1: Fecha | C1: Hora sugerida | D1: Plataforma | E1: Qué publicas | F1: Guion
A2: Lunes | B2: 2026-10-12 | C2: 07:00 | D2: Spotify (podcast) | E2: Episodio del día (8–10 min): Dinero | F2: Intro: "Bienvenida a Las Fórmulas Cuánticas para Hackear tu Mente y la Matrix. Soy Mabel Soriano y hoy hablamos de dinero." Pieza 1: 3 señales de que tu mente rechaza el dinero Pieza 2: Di esto cada vez que pagues algo Pieza 3: El cheque de 10 millones de jim carrey Cierre: "Si este episodio te movió algo, compártelo con alguien que lo necesite. Lo que no se activa, no cambia."
A3: Martes | B3: 2026-10-13 | C3: 07:00 | D3: Spotify (podcast) | E3: Episodio del día (8–10 min): Ansiedad y estrés | F3: Intro: "Bienvenida a Las Fórmulas Cuánticas para Hackear tu Mente y la Matrix. Soy Mabel Soriano y hoy hablamos de ansiedad y estrés." Pieza 1: 3 señales de ansiedad que crees que son tu personalidad Pieza 2: El suspiro que baja la ansiedad en 1 minuto Pieza 3: 15 minutos de escritura que calman tu mente Cierre: "Si este episodio te movió algo, compártelo con alguien que lo necesite. Lo que no se activa, no cambia."
A4: Miércoles | B4: 2026-10-14 | C4: 07:00 | D4: Spotify (podcast) | E4: Episodio del día (8–10 min): Relaciones | F4: Intro: "Bienvenida a Las Fórmulas Cuánticas para Hackear tu Mente y la Matrix. Soy Mabel Soriano y hoy hablamos de relaciones." Pieza 1: 3 señales de que no es amor, es enganche Pieza 2: Corta el cordón con este decreto Pieza 3: Beyoncé tenía un alter ego: sasha fierce Cierre: "Si este episodio te movió algo, compártelo con alguien que lo necesite. Lo que no se activa, no cambia."
A5: Jueves | B5: 2026-10-15 | C5: 07:00 | D5: Spotify (podcast) | E5: Episodio del día (8–10 min): Vacío y despertar | F5: Intro: "Bienvenida a Las Fórmulas Cuánticas para Hackear tu Mente y la Matrix. Soy Mabel Soriano y hoy hablamos de vacío y despertar." Pieza 1: 3 señales de que estás despertando (y por qué duele) Pieza 2: Ritual de 3 minutos para volver a ti Pieza 3: Lo que steve jobs dijo sobre unir los puntos Cierre: "Si este episodio te movió algo, compártelo con alguien que lo necesite. Lo que no se activa, no cambia."
A6: Viernes | B6: 2026-10-16 | C6: 07:00 | D6: Spotify (podcast) | E6: Episodio del día (8–10 min): Energía y salud | F6: Intro: "Bienvenida a Las Fórmulas Cuánticas para Hackear tu Mente y la Matrix. Soy Mabel Soriano y hoy hablamos de energía y salud." Pieza 1: 3 señales de que tu cuerpo no descansa aunque duermas Pieza 2: Decreto para apagar la alerta antes de dormir Pieza 3: La oms ya le puso nombre a tu agotamiento Cierre: "Si este episodio te movió algo, compártelo con alguien que lo necesite. Lo que no se activa, no cambia."
A7: Sábado | B7: 2026-10-17 | C7: 07:00 | D7: Spotify (podcast) | E7: Episodio del día (8–10 min): Metas y comunidad | F7: Intro: "Bienvenida a Las Fórmulas Cuánticas para Hackear tu Mente y la Matrix. Soy Mabel Soriano y hoy hablamos de metas y comunidad." Pieza 1: 3 razones por las que abandonas tus metas Pieza 2: Decreta tu meta conmigo en voz alta Pieza 3: La pregunta que el papá de sara blakely le hacía Cierre: "Si este episodio te movió algo, compártelo con alguien que lo necesite. Lo que no se activa, no cambia."
A8: Domingo | B8: 2026-10-18 | C8: 07:00 | D8: Spotify (podcast) | E8: Episodio del día (8–10 min): Valor puro (sin venta) | F8: Intro: "Bienvenida a Las Fórmulas Cuánticas para Hackear tu Mente y la Matrix. Soy Mabel Soriano y hoy hablamos de valor puro (sin venta)." Pieza 1: 3 preguntas para cerrar tu semana Pieza 2: Mi tdah no era un déficit, era una antena Pieza 3: Llave de luz: abre tu semana con este decreto Cierre: "Si este episodio te movió algo, compártelo con alguien que lo necesite. Lo que no se activa, no cambia."
A9: Domingo | B9: 2026-10-18 | C9: 10:00 | D9: YouTube (largo) | E9: Por qué repites la misma historia en el amor (y cómo cortar el enganche) | F9: 1. Gancho (0:00–0:30): «No es que lo ames demasiado. Es que tu cerebro está enganchado.» 2. Las 3 señales del enganche (miércoles, pieza 1) y el experimento de Skinner, explicado simple. 3. Por qué eliges siempre el mismo tipo de persona: lo familiar no es lo sano. [Tu historia real.] 4. El ritual de corte de cordón, hecho en vivo con quien te ve (miércoles, pieza 2). 5. Tu alter ego en el amor: 3 cosas que hace tu versión fuerte (miércoles, pieza 3). 6. Cierre: «Comenta LIBRE si lo hiciste conmigo» + suscríbete. Sin venta.
A11: Horas del podcast y del YouTube: sin dato propio todavía (s/d). Son sugerencia.

Sheet Querido Ex
A1: Audio | B1: Tema | C1: Duración | D1: Fórmula | E1: Frase del día | F1: Ejercicio | G1: GUION COMPLETO (lo que lees) | H1: ¿Grabado?
A2: Audio 0 | B2: Bienvenida | C2: 5–6 min | D2: — | E2: — | F2: — | G2: Hola. Bienvenida a Querido Ex: 7 días para cortar el enganche y volver a ti. Soy Mabel Soriano, y antes de empezar quiero decirte algo: si estás aquí, no es porque seas débil. Es porque una parte de ti ya está cansada de dar vueltas en lo mismo. Y esa parte es la que hoy decidió activarse. [pausa] Seguramente ya lo intentaste todo. Te prometiste no volver a revisar sus historias… y las revisaste. Borraste su número… y te lo sabes de memoria. Le dijiste a tus amigas "ya lo superé"… y en la noche volviste a pensar en él. [pausa] No estás loca. Estás enganchada. Y el enganche no se rompe con fuerza de voluntad. Se rompe entendiendo cómo funciona tu software neurológico y cortando, paso a paso, los canales por donde se te escapa la energía. Eso es lo que vamos a hacer en estos 7 días. Cómo funciona: Cada día tienes un audio como este, de unos 10 minutos. Escúchalo con audífonos, en un lugar donde nadie te interrumpa. De preferencia en la noche, antes de dormir, o en la mañana antes de agarrar el celular. Después del audio hay un ritual o ejercicio de 5 minutos. Está en tu PDF. No te lo saltes. El audio te hace entender; el ejercicio es lo que activa el cambio en tu cuerpo. Y cada día tienes una frase. Escríbela donde la veas: en un post-it, en el fondo de pantalla, en el espejo. Tres acuerdos contigo misma antes de empezar: Uno: un día a la vez. No te adelantes. Cada día prepara el terreno del siguiente. Dos: sin juicio. Si un día recaes y le escribes, o revisas su perfil, no empiezas de cero. Respiras, regresas al audio de ese día y sigues. Recaer no es fracasar; es información. Tres: esto es para ti, no para que él regrese. Te lo digo con todo mi amor: este proceso no es para hacer que vuelva. Es para que tú vuelvas a ti. Y cuando tú vuelves a ti, eliges desde otro lugar. [pausa] Algo importante: Si estás en una relación donde hay violencia, golpes, amenazas, o te sientes en riesgo, este proceso no sustituye la ayuda profesional. Busca apoyo. En México puedes llamar a la Línea de la Vida: 800 911 2000, las 24 horas. Pedir ayuda también es soberanía. [pausa] Y una cosa más: Durante estos 7 días vas a sentir cosas. A veces alivio, a veces tristeza, a veces enojo. Todo está permitido. No vinimos a tapar lo que sientes; vinimos a transmutarlo. Así que respira conmigo. [pausa] Pon una mano en tu pecho. [pausa] Y repite en silencio: "Hoy elijo volver a mí." [pausa] "Hoy elijo volver a mí." [pausa] "Hoy elijo volver a mí." Hecho está. Nos vemos en el Día 1. Ahí empezamos a entender por qué no puedes dejar de pensarle… y por qué no es tu culpa. Te abrazo.
A3: Día 1 | B3: No estás loca, estás enganchada | C3: 10–11 min | D3: F | E3: "No es debilidad. Es un programa. Y los programas se cambian." | F3: La carta que no se envía. | G3: Bienvenida al Día 1. Quiero empezar con una pregunta, y quiero que la contestes con honestidad, solo para ti: ¿cuántas veces pensaste en él hoy? [pausa] No te juzgues por la respuesta. Solo obsérvala. Ahora te voy a explicar por qué pasa esto, porque cuando entiendes el mecanismo, dejas de pelearte contigo. Tu cerebro no extraña a la persona. Extraña la sensación. Cuando estabas con él, tu cuerpo aprendió a asociar su mensaje, su voz, su atención, con una sensación de alivio. Cada "buenos días", cada "te extraño", era como una pequeña recompensa. Y cuando esa persona era intermitente, a veces sí y a veces no, el enganche se volvía más fuerte. Porque tu sistema nunca sabía cuándo llegaba la siguiente dosis. [pausa] Por eso revisas el celular. Por eso ves sus historias. Por eso relees conversaciones viejas. No es que seas obsesiva. Es que tu software neurológico está buscando esa recompensa que aprendió. Y aquí está lo importante: eso no es amor. Es un circuito. Y un circuito se puede interrumpir. ¿Qué es el enganche, en lenguaje BNQ? Tu hardware biológico, tu cuerpo, guarda la memoria de esa relación: el olor, la voz, la forma en que te abrazaba. Tu software neurológico, tu mente, repite las mismas conversaciones y los mismos "y si…". Y tu energía, tu campo, sigue conectada a esa persona, como si hubiera un cable que no se ha desconectado. Cuerpo, mente y energía están jalando hacia el mismo lado. Por eso cuesta tanto. En estos 7 días vamos a trabajar los tres. Hoy empezamos por el primer paso: ponerle nombre a lo que sientes. [pausa] Coherencia Energética Integral La base de todo lo que hago es la Fórmula 01: Coherencia Energética Integral. Significa que lo que piensas, lo que sientes y lo que haces vayan en la misma dirección. Ahorita, probablemente, tu mente dice "ya no quiero sufrir", tu corazón dice "lo extraño", y tus manos agarran el celular para ver si se conectó. Tres direcciones distintas. Eso es incoherencia. Y la incoherencia agota. No vamos a forzar nada. Vamos a empezar por escuchar lo que sí está ahí. Ejercicio del día: la carta que no se envía Después de este audio, abre tu PDF. Vas a escribir una carta que empieza así: "Querido ex…" Y vas a escribir todo. Lo que nunca le dijiste. Lo que te dolió. Lo que extrañas. Lo que te enoja. Lo que te avergüenza haber hecho. Sin filtro, sin ortografía, sin ser linda. Esta carta no se envía. Nunca. Es para sacar del cuerpo lo que tu mente lleva días repitiendo. Cuando termines, la doblas y la guardas. El Día 7 vamos a hacer algo con ella. [pausa] Antes de irte, respira conmigo. Cierra los ojos. [pausa] Inhala en 4… 1, 2, 3, 4. [pausa] Sostén en 4… 1, 2, 3, 4. [pausa] Exhala en 6… 1, 2, 3, 4, 5, 6. [pausa] Otra vez. Inhala… sostén… exhala largo. [pausa larga] Una vez más. [pausa larga] Pon tu mano en el pecho. Siente tu corazón. Ese corazón ha aguantado mucho. [pausa] Repite en silencio: "No es debilidad. Es un programa. Y los programas se cambian." [pausa] "No es debilidad. Es un programa. Y los programas se cambian." [pausa] "No es debilidad. Es un programa. Y los programas se cambian." Hecho está. Hoy diste el primer paso: dejaste de pelearte contigo. Escribe tu carta. Y mañana, en el Día 2, vamos a cortar el canal por donde más se te escapa la energía: tu celular. Te abrazo.
A4: Día 2 | B4: Corta el canal | C4: 9–10 min | D4: F | E4: "Mi atención es mi energía. Hoy la recupero." | F4: Pausa digital de 7 días. | G4: Bienvenida al Día 2. Antes de empezar, una pregunta: ¿escribiste tu carta? Si sí, te felicito. Eso que sacaste ya no lo cargas sola. Si todavía no, no pasa nada: hazla hoy, antes o después de este audio. Hoy vamos a hablar de algo muy práctico. Algo que parece pequeño, pero que es donde más energía se te está yendo: tu celular. Donde va tu atención, va tu energía. Piensa en esto. Cada vez que abres su perfil, cada vez que ves si se conectó, cada vez que relees un chat, le estás mandando energía. Literal. Tu atención es energía, y la estás depositando en alguien que ya no está. Y lo más injusto: mientras tú estás en tu casa revisando, drenada, él probablemente está en su vida, sin saber nada de esto. Tú alimentas el cable. Él ni siquiera lo siente. [pausa] Por eso hoy no vamos a hacer meditación profunda. Hoy vamos a hacer algo más poderoso: cerrar la llave. La pausa digital de 7 días Escúchame bien: no te estoy pidiendo que lo bloquees para siempre ni que hagas una escena. Te estoy pidiendo 7 días de pausa. Solo lo que dura este proceso. Esto es lo que vas a hacer, hoy mismo, después del audio: Uno: silencia sus historias y publicaciones. En Instagram, TikTok, Facebook, WhatsApp. Silenciar, no bloquear. Él no se entera. Tú dejas de ver. Dos: archiva el chat. Que no aparezca en tu pantalla principal. Si te sientes lista, bórralo. Si no, archívalo. Las dos cosas cuentan. Tres: quita las fotos de tu galería principal. Pásalas a una carpeta oculta o a la nube. No tienes que borrarlas. Solo que no te salten cuando abres tu celular. Cuatro: avísale a una persona de confianza. Dile: "Estoy haciendo 7 días para soltar. Si te escribo para preguntarte si le escribo, dime que no." Y ya. [pausa] Si tienen hijos o asuntos pendientes: la comunicación queda solo para lo necesario. Mensajes cortos, claros, sobre los niños o el tema práctico. Nada de "¿cómo estás?". Nada de revisar si leyó. ¿Y si me da ansiedad? Te va a dar. Es normal. Tu sistema va a buscar su dosis y no la va a encontrar. Vas a sentir el impulso de abrir el celular. Cuando pase, haz esto: pon la mano en el pecho y di en voz baja: "Mi atención es mi energía. Hoy la recupero." Y cambia de actividad. Lávate la cara, sal a caminar, pon una canción. El impulso dura unos minutos. Si no lo alimentas, baja. El Día 5 te voy a dar un protocolo completo de emergencia para esos momentos. Por ahora, esta frase es tu ancla. [pausa] Respira conmigo. Cierra los ojos. [pausa] Imagina que de tu pecho sale un hilo de luz hacia tu celular. Por ese hilo se te está yendo energía cada vez que lo abres para buscarlo. [pausa] Ahora, imagina que ese hilo regresa hacia ti. Que la luz vuelve a tu pecho. [pausa] Inhala… y siente cómo esa energía regresa a tu cuerpo. [pausa] Exhala… y suelta el impulso de buscar. [pausa] Otra vez. Inhala, recuperas. Exhala, sueltas. [pausa larga] Repite en silencio: "Mi atención es mi energía. Hoy la recupero." [pausa] "Mi atención es mi energía. Hoy la recupero." [pausa] "Mi atención es mi energía. Hoy la recupero." Hecho está. Ahora ve y haz tu pausa digital. Son 10 minutos. Es el paso más práctico de todo el proceso, y el que más vas a notar. Mañana, en el Día 3, vamos a trabajar el cable que no se ve: el cordón energético. Te veo ahí.
A5: Día 3 | B5: El cordón | C5: 12 min | D5: F | E5: "Te devuelvo lo que es tuyo. Recupero lo que es mío." | F5: Ritual de corte de cordón con vela (después del audio o al día siguiente). | G5: Bienvenida al Día 3. ¿Cómo te fue con tu pausa digital? Si lo hiciste, hoy tu celular ya no es el mismo campo de batalla. Si recaíste y revisaste algo, respira. No empiezas de cero. Hoy es un buen día para volver. Hoy vamos a trabajar lo que no se ve. Ayer cortamos el canal del celular. Hoy vamos a trabajar el cordón energético. ¿Qué es un cordón? Cuando compartes tu vida con alguien, tu tiempo, tu cuerpo, tus secretos, tus planes, se crea un lazo. En muchas tradiciones espirituales a ese lazo se le llama cordón. Es la conexión energética que sigue ahí aunque la relación ya terminó. Por eso a veces sientes que "lo sientes" aunque no lo veas. Por eso piensas en él justo cuando él publica algo. No es casualidad: es que todavía hay un canal abierto. [pausa] Hoy no vamos a cortar con odio. Vamos a cortar con amor. Porque lo que se corta con odio, se vuelve a amarrar. Lo que se suelta con gratitud, se libera. Busca un lugar cómodo. Siéntate o recuéstate. Si estás manejando, detén este audio y escúchalo después. Meditación de corte de cordón Cierra los ojos. [pausa] Respira profundo… inhala por la nariz… y exhala por la boca, despacio. [pausa] Otra vez. Inhala… exhala. [pausa] Siente el peso de tu cuerpo. Tus pies. Tus piernas. Tu espalda. Tus hombros… suéltalos. [pausa] Ahora lleva tu atención al centro de tu frente, entre las cejas. Ahí vive tu glándula pineal, tu antena. Imagina una luz suave ahí, que se enciende. [pausa] Baja esa luz hacia tu corazón. Siente cómo tu frente y tu corazón se conectan con un hilo de luz. Mente y corazón, juntos. [pausa larga] Ahora imagina que frente a ti, a unos metros, aparece él. No tienes que verlo con detalle. Solo siente su presencia. [pausa] Observa. Entre tú y él hay uno o varios cordones. Puede que salgan de tu pecho, de tu estómago, de tu garganta. Solo obsérvalos. ¿De qué color son? ¿Son delgados o gruesos? [pausa larga] No pasa nada. Estás a salvo. Esto es solo energía que vamos a regresar a su lugar. Ahora, mírale y dile en tu mente: "Gracias por lo que aprendí contigo." [pausa] "Te devuelvo lo que es tuyo." [pausa] Imagina que todo lo que él dejó en ti, sus palabras, sus promesas, su energía, regresa a él por el cordón, como una luz que se va. [pausa larga] "Recupero lo que es mío." [pausa] Ahora imagina que todo lo que tú dejaste en él, tu tiempo, tu ilusión, tu energía, regresa a ti. Vuelve a tu pecho. Te llenas de tu propia luz. [pausa larga] Ahora, en tu mano derecha, aparece una espada de luz. Es tuya. Es tu soberanía energética. [pausa] Con amor, con calma, sin rabia… vas a cortar los cordones. Uno por uno. Primero el del pecho. Corta. [pausa] El del estómago. Corta. [pausa] El de la garganta. Corta. [pausa] Cualquier otro que veas. Corta. [pausa larga] Observa cómo los extremos de los cordones se disuelven en luz. Del lado de él, y del lado tuyo. [pausa] Pon tu mano donde estaba cada cordón y sella esa zona con luz dorada. Como si pusieras una venda de luz. [pausa larga] Mira cómo él se aleja. Se va por su camino. Tú te quedas en el tuyo. Sin rencor. En paz. [pausa larga] Repite conmigo: "Te devuelvo lo que es tuyo. Recupero lo que es mío." [pausa] "Te devuelvo lo que es tuyo. Recupero lo que es mío." [pausa] "Te devuelvo lo que es tuyo. Recupero lo que es mío." [pausa] Espada de luz, espada de luz, espada de luz. Hecho está. [pausa] Respira profundo. Mueve suavemente tus manos, tus pies. Cuando estés lista, abre los ojos. [pausa] Tu ritual con vela En tu PDF está el ritual físico: una vela blanca, un hilo o listón, y el mismo decreto. Puedes hacerlo hoy o mañana. El cuerpo necesita también el acto físico para cerrar lo que la mente ya entendió. Si hoy te sientes cansada o sensible, es normal. Toma agua, descansa, duérmete temprano. Mañana, en el Día 4, vamos a ver algo que te va a abrir los ojos: por qué te enganchaste justo con él. Spoiler: no era él. Era el patrón. Te abrazo.
A6: Día 4 | B6: No era él, era el patrón | C6: 10–11 min | D6: F | E6: "Veo el patrón. Ya no soy el patrón." | F6: "¿A quién me recordaba?" (3 preguntas por escrito). | G6: Bienvenida al Día 4. Ya vas a la mitad. ¿Cómo te sentiste después del corte de cordón? Hay quien siente ligereza, hay quien siente tristeza, hay quien no siente nada especial. Las tres respuestas están bien. La energía se acomoda a su ritmo. Hoy vamos a hacer algo distinto. Hoy no vamos a hablar de él. Vamos a hablar de ti. Porque hay una pregunta que lo cambia todo: ¿por qué con él? Tu subconsciente elige antes que tú Hay algo que casi nadie te explica: la mayor parte de lo que haces en el día lo haces en automático, desde tu subconsciente. Y tu subconsciente aprendió qué es el amor mucho antes de que tuvieras tu primera pareja. Lo aprendió viendo a tus papás, a tu familia, a las personas que te cuidaron… o que no te cuidaron. [pausa] Si aprendiste que el amor era esperar, vas a sentir "química" con quien te hace esperar. Si aprendiste que el amor había que ganárselo, vas a sentir "química" con quien te hace demostrar que vales. Si aprendiste que el amor se iba, vas a sentir "química" con quien nunca termina de quedarse. Y a la persona que te trata bien, que te escribe, que es clara… le vas a decir "es que no siento nada". [pausa] No es que tengas mal gusto. Es que tu software neurológico reconoce como "amor" lo que le es familiar. Y lo familiar no siempre es lo sano. Entonces, ¿qué fue él? Él fue un espejo. Te mostró, con mucha claridad, un programa que ya estaba en ti. Por eso dolió tanto. No solo perdiste a una persona: se activó una herida vieja. Y esto es una buena noticia. Porque si el patrón está en ti, tú puedes cambiarlo. No depende de que él cambie, ni de que llegue alguien "diferente". Si no cambias el programa, la siguiente persona va a tener otra cara… y la misma historia. Lo que sí se puede hacer: verlo. Lo que se ve, deja de manejarte en automático. [pausa] Ejercicio del día: "¿A quién me recordaba?" Después del audio, abre tu PDF y contesta estas 3 preguntas por escrito. Escribe lo primero que te llegue, sin pensarlo mucho: Pregunta 1: ¿Qué sentía yo con él que ya había sentido antes, en mi infancia o en otra relación? Por ejemplo: esperar, rogar, no ser suficiente, tener que adivinar, sentirme invisible. Pregunta 2: ¿A quién de mi historia me recordaba su forma de tratarme? Puede ser tu papá, tu mamá, un hermano, una expareja. No para culpar a nadie: solo para ver. Pregunta 3: ¿Qué hacía yo para que me quisiera? Por ejemplo: aguantar, complacer, callarme, estar siempre disponible. Cuando termines, lee tus respuestas en voz alta. Y al final escribe: "Veo el patrón. Ya no soy el patrón." [pausa] Respira conmigo. Cierra los ojos. [pausa] Imagina a la niña que fuiste. Tal vez de 5, 6, 7 años. Mírala. ¿Cómo está? ¿Qué necesitaba en ese momento? [pausa larga] Acércate a ella. Agáchate a su altura. Y dile: "No era tu culpa. Tú no tenías que ganarte el amor." [pausa larga] "Ahora yo te cuido." [pausa larga] Abrázala. Siente cómo se calma. Siente cómo tú también te calmas. [pausa larga] Respira. Inhala… exhala. [pausa] Repite en silencio: "Veo el patrón. Ya no soy el patrón." [pausa] "Veo el patrón. Ya no soy el patrón." [pausa] "Veo el patrón. Ya no soy el patrón." Hecho está. Si este ejercicio movió mucho, es normal. Si sientes que tocaste algo profundo que necesita más acompañamiento, eso también es información valiosa. Ir a la raíz de estos patrones es justo lo que trabajo en mis niveles. Mañana, en el Día 5, te doy tu herramienta de emergencia: qué hacer en esos 3 minutos en los que sientes que le vas a escribir. Te abrazo.
A7: Día 5 | B7: El vacío que deja | C7: 10 min | D7: F | E7: "Este impulso pasa. Yo me quedo." | F7: Protocolo de emergencia de 3 minutos (tarjeta para guardar en el celular). | G7: Bienvenida al Día 5. Ayer viste el patrón. Hoy vamos a trabajar el momento más difícil de todo este proceso: ese momento en el que tienes el celular en la mano y estás a punto de escribirle. Lo conoces. Es de noche, o es domingo, o viste algo que te lo recordó. Y de repente sientes un hueco en el estómago, un vacío, una urgencia. Y tu mente empieza: "solo le pregunto cómo está", "solo le mando una canción", "solo para cerrar bien". [pausa] Hoy te voy a dar una herramienta para ese momento. ¿Qué es ese vacío? Ese vacío no es amor. Es tu sistema nervioso en alerta. Cuando algo que te daba seguridad desaparece, tu cuerpo lo vive como una amenaza. Se acelera el corazón, se aprieta el pecho, sientes urgencia. Tu cuerpo te dice "haz algo ya". Y la acción que tu cuerpo conoce para calmarse es… buscarlo. Pero escribirle no calma el vacío. Lo alimenta. Porque si te contesta, tu sistema aprende que el vacío se calma con él. Y si no te contesta, el vacío se hace más grande. [pausa] La salida es enseñarle a tu cuerpo otra forma de calmarse. Eso es coherencia: que tu mente, tu corazón y tu cuerpo regresen a ti en lugar de ir hacia él. Protocolo de emergencia de 3 minutos Esto es lo que vas a hacer cada vez que sientas el impulso. Guárdalo en tu celular. Está en tu PDF como tarjeta. Paso 1 — Suelta el celular. (10 segundos) Ponlo boca abajo, lejos de tu mano. No tienes que decidir nada todavía. Solo suéltalo. Paso 2 — Respiración 4-4-6. (1 minuto) Inhala en 4, sostén en 4, exhala en 6. Cinco veces. La exhalación larga le dice a tu cuerpo que no hay peligro. Paso 3 — Mano en el pecho y nombra lo que sientes. (30 segundos) "Siento ansiedad." "Siento tristeza." "Siento miedo a estar sola." Solo nombrarlo baja la intensidad. Paso 4 — Tu frase gatillo. (30 segundos) Tres veces: "Este impulso pasa. Yo me quedo." Paso 5 — Cambia de estado. (1 minuto) Muévete. Lávate la cara con agua fría, sal al patio, pon una canción y baila, escribe en tu libreta lo que le querías decir. Cualquier cosa que saque la energía del cuerpo. Después de esos 3 minutos, si todavía quieres escribirle… espera 24 horas. Si mañana sigues pensando que es buena idea, platícalo con tu persona de confianza. Casi siempre, al día siguiente, ya no hace falta. [pausa] Practiquémoslo juntas ahora. Imagina que ahorita tienes el impulso. Siente dónde vive en tu cuerpo. [pausa] Suelta lo que tengas en las manos. [pausa] Inhala… 1, 2, 3, 4. Sostén… 1, 2, 3, 4. Exhala… 1, 2, 3, 4, 5, 6. [pausa] Otra vez. [pausa larga] Otra vez. [pausa larga] Mano en el pecho. Nombra lo que sientes, en silencio. [pausa larga] Ahora repite: "Este impulso pasa. Yo me quedo." [pausa] "Este impulso pasa. Yo me quedo." [pausa] "Este impulso pasa. Yo me quedo." [pausa] Hielo azul, hielo azul, hielo azul. Que se enfríe la urgencia. Hecho está. ¿Notas la diferencia? No desapareció todo. Pero bajó. Y eso es lo que entrena tu cuerpo: cada vez que el impulso llega y no lo sigues, el circuito se debilita un poquito. Cada vez es más fácil. Mañana, en el Día 6, dejamos de hablar de él para siempre en este proceso. Vamos a ir a lo más bonito: volver a ti. Te abrazo.
A8: Día 6 | B8: Vuelve a ti | C8: 10–11 min | D8: F | E8: "Me elijo. Vuelvo a mí." | F8: Lista de 10 cosas que dejaste de hacer + elegir 1 para hoy. | G8: Bienvenida al Día 6. Llevas cinco días. Entendiste el enganche, cerraste el canal, cortaste el cordón, viste el patrón y aprendiste a sostenerte en el impulso. Eso es mucho. De verdad, date crédito. [pausa] Hoy no vamos a hablar de él. Hoy vamos a hablar de alguien que extrañas más de lo que crees: tú. ¿Dónde te quedaste? Cuando estamos en una relación que nos engancha, poco a poco nos vamos haciendo chiquitas. Dejamos de ver a nuestras amigas porque él se molestaba, o porque esperábamos su mensaje. Dejamos de hacer ejercicio, de pintar, de bailar, de leer. Dejamos de vestirnos como nos gustaba. Dejamos de decir lo que pensábamos para no pelear. Y un día te miras al espejo y no sabes bien quién eres sin esa persona. [pausa] Esa sensación de vacío que trabajamos ayer no es solo porque se fue él. Es porque tú te fuiste primero. Te fuiste de ti para quedarte con él. Hoy vamos a regresar. Tu Yo Superior te está esperando En la Fórmula 07 trabajamos la conexión con tu Yo Superior: la versión de ti que no está en modo supervivencia, que sabe quién es, que no necesita que nadie la elija para saber que vale. Esa versión no es una fantasía. Ya existe. La has visto en momentos en que te sentiste libre, segura, contenta sin razón. Solo hay que volver a encontrarla. Meditación: el encuentro Cierra los ojos. [pausa] Respira profundo. Inhala… exhala. [pausa] Imagina que estás caminando por un lugar que te da paz. Puede ser una playa, un bosque, un jardín. Siente el suelo bajo tus pies. [pausa larga] A lo lejos ves a una mujer. Camina tranquila. Se ve ligera, segura, radiante. Conforme se acerca, te das cuenta: eres tú. Eres tú en tu mejor versión. [pausa larga] Obsérvala. ¿Cómo se ve? ¿Cómo está vestida? ¿Cómo camina? ¿Cómo te mira? [pausa larga] Ella se detiene frente a ti. Te sonríe. Y te dice: "Te estaba esperando." [pausa larga] Pregúntale: "¿Qué necesito recuperar de mí?" Y escucha lo primero que te diga. Una palabra, una imagen, una sensación. [pausa larga] Ahora ella te toma de las manos. Y poco a poco, se funde contigo. Su luz entra en tu pecho. Su seguridad entra en tu cuerpo. Su calma entra en tu mente. [pausa larga] Ya no está afuera. Está en ti. Siempre estuvo. [pausa] Repite en silencio: "Me elijo. Vuelvo a mí." [pausa] "Me elijo. Vuelvo a mí." [pausa] "Me elijo. Vuelvo a mí." [pausa] Llave de luz, llave de luz, llave de luz. Se abre la puerta de regreso a ti. Hecho está. Respira. Cuando estés lista, abre los ojos. [pausa] Ejercicio del día Abre tu PDF y escribe una lista de 10 cosas que dejaste de hacer mientras estabas en esa relación o después de que terminó. Cosas que te hacían sentir tú. Grandes o pequeñas: ir al cine sola, cantar en el coche, ver a tu amiga, usar ese vestido, cocinar algo rico solo para ti. Después elige una. Solo una. Y hazla hoy, o mañana a más tardar. No es un premio. Es una declaración: "Aquí estoy de vuelta." Mañana es el Día 7, el cierre. Ten a la mano la carta que escribiste el Día 1. Vamos a cerrar el ciclo y a decidir qué eliges a partir de ahora. Te abrazo.
A9: Día 7 | B9: Lo que sí eliges | C9: 11–12 min | D9: F | E9: "Lo que no se activa, no cambia. Hoy me activo." | F9: Carta de cierre (se quema o se guarda) + decreto final. | G9: Bienvenida al Día 7. El último. Antes de empezar, quiero que te detengas un momento y mires hacia atrás. Hace una semana estabas en otro lugar. Tal vez revisabas su perfil varias veces al día. Tal vez no podías dormir. Tal vez sentías que esto no iba a pasar nunca. [pausa] Hoy, aunque todavía duela un poco, ya no eres la misma. Entendiste el enganche. Cerraste el canal. Cortaste el cordón. Viste el patrón. Aprendiste a sostenerte. Y volviste a ti. Eso es una activación. Y lo hiciste tú. Hoy cerramos el ciclo Ten a la mano la carta que escribiste el Día 1, la que empezaba con "Querido ex…". [pausa] Léela en silencio. Despacio. [pausa larga] ¿Notas algo distinto? Tal vez algunas frases ya no te duelen igual. Tal vez otras sí. Todo está bien. Esa carta fue la fotografía de dónde estabas. Hoy ya no estás ahí. Tu carta de cierre Ahora, en una hoja nueva, vas a escribir una carta de cierre. Esta es corta. Tiene tres partes: Primera parte — Gracias. "Gracias por…" Lo que aprendiste, lo que viviste, lo que te mostró de ti. Aunque haya dolido. Segunda parte — Te suelto. "Te suelto y te dejo ir a tu camino. Yo me quedo en el mío." Tercera parte — Me elijo. "A partir de hoy elijo…" Y aquí escribes qué tipo de vínculo aceptas desde hoy. Sé concreta. Por ejemplo: "Elijo a alguien que sea claro conmigo." "Elijo no rogar." "Elijo relaciones donde no tenga que adivinar." "Elijo primero mi paz." Pausa este audio si necesitas tiempo para escribirla. Aquí te espero. [pausa larga] Ritual de cierre Ahora tienes dos cartas. La del Día 1 representa lo que fue. La de cierre representa lo que eliges. Con la del Día 1 puedes hacer dos cosas: quemarla con cuidado en un recipiente seguro, o romperla en pedacitos y tirarla. Lo que se quema o se rompe, se transmuta. Es tu forma de decirle a tu cuerpo: "esto ya terminó." La carta de cierre la guardas. En tu buró, en tu libreta, donde la puedas leer cuando la necesites. Si vas a quemar, prende tu vela. Hazlo con calma y con cuidado. [pausa larga] Decreto final Pon tus manos en el pecho. Cierra los ojos. [pausa] Respira profundo… inhala… exhala. [pausa] Siente tu corazón. Siente tu cuerpo. Siente que estás aquí, completa. [pausa] Repite conmigo, en voz alta si puedes: "Hoy cierro este ciclo con amor." [pausa] "Lo que fue, fue. Lo agradezco y lo suelto." [pausa] "Mi energía es mía. Mi atención es mía. Mi vida es mía." [pausa] "Elijo vínculos claros, recíprocos y en paz." [pausa] "Me elijo. Vuelvo a mí." [pausa] "Lo que no se activa, no cambia. Hoy me activo." [pausa] Hecho está. Hecho está. Hecho está. [pausa larga] Respira. Abre los ojos. Lo que sigue Escúchame bien: soltar no es una línea recta. Habrá días buenos y días en que te acuerdes. Eso no significa que no funcionó. Significa que eres humana. Cuando pase, regresa al audio que necesites: el Día 3 si sientes la conexión, el Día 5 si te gana el impulso, el Día 6 si te pierdes de ti. Y si en estos días te diste cuenta de que hay un patrón más profundo, algo que viene de mucho antes de él, ese es el trabajo que hacemos en el Nivel 1. Ahí vamos a la raíz. Cuando estés lista, ahí te espero. Gracias por elegirte estos 7 días. De verdad, gracias. Querido ex… gracias. Y adiós. Te abrazo fuerte.

Sheet Competencia
A1: # | B1: Red | C1: Cuenta | D1: Fecha | E1: PIEZA (link) | F1: HOOK (primera frase) | G1: TIPO DE HOOK | H1: TEMA | I1: FORMATO | J1: DURACIÓN | K1: EMOCIÓN | L1: CTA | M1: Vistas | N1: Mediana de la cuenta | O1: RENDIMIENTO (vistas ÷ mediana) | P1: PATRÓN | Q1: Archivo de la transcripción
A2: 1 | B2: Instagram | C2: @danielacorreaup | D2: 2026-07-25 | E2: https://www.instagram.com/p/DbMptmRtnU5/ | F2: Las personas con TDAH no tienen un déficit de atención, tienen un exceso de atención para lo que realmente les importa. | G2: G1 · Reencuadre | H2: TDAH / neurodivergencia | I2: Cara a cámara | J2: 71 s | K2: Sorpresa / alivio | L2: Ninguno | M2: 2500753 | N2: 4071.5 | O2: =IFERROR(M2/N2,"s/d") | P2: P1 · Romper creencia + nombre propio al problema | Q2: transcripciones/instagram-2026-07-25-esta-es-la-ventaja-de-las.md
A3: 2 | B3: Instagram | C3: @danielacorreaup | D3: 2026-09-17 | E3: https://www.instagram.com/p/DdXi3VJtZo0/ | F3: Odian los ruidos fuertes, pero pueden escuchar la misma canción durante cinco horas. | G3: G5 · Espejo | H3: TDAH / neurodivergencia | I3: Cara a cámara rápido | J3: 34 s | K3: Identificación | L3: Ninguno | M3: 2166685 | N3: 4071.5 | O3: =IFERROR(M3/N3,"s/d") | P3: P5 · Lista o espejo de señales | Q3: transcripciones/instagram-2026-09-17-contradicciones-de-personas-neurodivergentes.md
A4: 3 | B4: TikTok | C4: @mabradiante | D4: 2025-08-18 | E4: https://www.tiktok.com/@mabradiante/video/7539939568632581392 | F4: Di esto en tu casa y mira cómo todo comienza a cambiar. | G4: G2 · Promesa práctica | H4: Hogar / energía | I4: Cara a cámara + decreto | J4: 163 s | K4: Esperanza | L4: Comenta HECHO ESTÁ + guarda y comparte | M4: 2200000 | N4: 11850 | O4: =IFERROR(M4/N4,"s/d") | P4: P2 · Herramienta para usar ya (decreto, ritual, técnica) | Q4: transcripciones/tiktok-2025-08-18-di-esto-en-tu-casa-y.md
A5: 4 | B5: Instagram | C5: @danielacorreaup | D5: 2026-06-16 | E5: https://www.instagram.com/p/DZoPOQoNlb5/ | F5: (texto en pantalla) La física ya lo confirmó: lo que no puedes ver es lo que construye todo lo que sí ves. | G5: G6 · Autoridad científica | H5: Energía / despertar | I5: Texto en pantalla + música | J5: 28 s | K5: Asombro | L5: s/d | M5: 554163 | N5: 4071.5 | O5: =IFERROR(M5/N5,"s/d") | P5: P9 · Texto en pantalla + música (sin voz) | Q5: transcripciones/instagram-2026-06-16-la-fisica-ya-lo-confirmo.md
A6: 5 | B6: TikTok | C6: @mabradiante | D6: 2023-09-13 | E6: https://www.tiktok.com/@mabradiante/video/7278395420961688837 | F6: Cambia tu vida con palabras gatillo: qué son, para qué sirven, cómo se hacen. | G6: G2 · Promesa práctica | H6: Espiritualidad práctica | I6: Cara a cámara + lista de 5 | J6: 84 s | K6: Curiosidad | L6: Corazón y compártelo | M6: 628600 | N6: 11850 | O6: =IFERROR(M6/N6,"s/d") | P6: P2 · Herramienta para usar ya (decreto, ritual, técnica) | Q6: transcripciones/tiktok-2023-09-13-cambia-tu-vida-con-palabras-gatillo.md
A7: 6 | B7: TikTok | C7: @mabradiante | D7: 2025-01-16 | E7: https://www.tiktok.com/@mabradiante/video/7460335723938385157 | F7: Cuidado con este video porque vamos a desbloquear tu riqueza. | G7: G2 · Promesa práctica | H7: Dinero | I7: Cara a cámara + decreto guiado | J7: 145 s | K7: Esperanza | L7: Comenta YO QUIERO | M7: 556700 | N7: 11850 | O7: =IFERROR(M7/N7,"s/d") | P7: P2 · Herramienta para usar ya (decreto, ritual, técnica) | Q7: transcripciones/tiktok-2025-01-16-cuidado-con-este-video-porque-vamos.md
A8: 7 | B8: Instagram | C8: @danielacorreaup | D8: 2026-09-05 | E8: https://www.instagram.com/p/Dc7CLvtBsBD/ | F8: Uno de los superpoderes de la neurodivergencia es tu capacidad de obsesionarte… | G8: G1 · Reencuadre | H8: TDAH / neurodivergencia | I8: Cara a cámara | J8: 83 s | K8: Orgullo | L8: Ninguno | M8: 171167 | N8: 4071.5 | O8: =IFERROR(M8/N8,"s/d") | P8: P1 · Romper creencia + nombre propio al problema | Q8: transcripciones/instagram-2026-09-05-este-es-uno-de-los-super.md
A9: 8 | B9: Instagram | C9: @quantumquip | D9: 2026-09-26 | E9: https://www.instagram.com/p/Ddwnt0FPrfM/ | F9: (caption) Cuando entrenas lo suficiente a tu atención para acompañarte… | G9: G2 · Práctica | H9: Emociones / presencia | I9: Texto en pantalla + música | J9: 46 s | K9: s/d | L9: s/d | M9: 174917 | N9: 4530 | O9: =IFERROR(M9/N9,"s/d") | P9: P9 · Texto en pantalla + música (sin voz) | Q9: transcripciones/instagram-2026-09-26-cuando-entrenas-lo-suficiente-a-tu.md
A10: 9 | B10: Instagram | C10: @danielacorreaup | D10: 2026-08-22 | E10: https://www.instagram.com/p/DcUlSiytrS_/ | F10: Sabrina Carpenter es el ejemplo perfecto de cómo funciona la manifestación. | G10: G9 · Ejemplo famoso | H10: Manifestación / identidad | I10: Cara a cámara | J10: 51 s | K10: Inspiración | L10: Ninguno | M10: 144483 | N10: 4071.5 | O10: =IFERROR(M10/N10,"s/d") | P10: P7 · Autoridad: estudio, famoso o cita | Q10: transcripciones/instagram-2026-08-22-sabrina-carpenter-es-el-ejemplo-perfecto.md
A11: 10 | B11: Instagram | C11: @danielacorreaup | D11: 2026-08-15 | E11: https://www.instagram.com/p/DcC8I3KN9kI/ | F11: Alguien dijo que las personas con la forma de pensar más avanzada tienen una habilidad muy particular. | G11: G6 · Autoridad | H11: Identidad / inteligencia | I11: Cara a cámara | J11: 45 s | K11: Orgullo / curiosidad | L11: Compártelo | M11: 127947 | N11: 4071.5 | O11: =IFERROR(M11/N11,"s/d") | P11: P7 · Autoridad: estudio, famoso o cita | Q11: transcripciones/instagram-2026-08-15-esta-es-la-manera-de-pensar.md
A12: 11 | B12: Instagram | C12: @danielacorreaup | D12: 2026-09-02 | E12: https://www.instagram.com/p/DcxHcIpN2jw/ | F12: Solo existen dos tipos de personas que ganan en la vida. | G12: G5 · Lista | H12: Metas / éxito | I12: Cara a cámara | J12: 50 s | K12: Curiosidad | L12: Ninguno | M12: 121918 | N12: 4071.5 | O12: =IFERROR(M12/N12,"s/d") | P12: P5 · Lista o espejo de señales | Q12: transcripciones/instagram-2026-09-02-que-tipo-de-persona-eres.md
A13: 12 | B13: TikTok | C13: @mabradiante | D13: 2025-04-11 | E13: https://www.tiktok.com/@mabradiante/video/7491928239577861382 | F13: Cuidado con este video porque esta es una oración para conectar con la abundancia. | G13: G2 · Promesa práctica | H13: Dinero / abundancia | I13: Cara a cámara + oración guiada | J13: 176 s | K13: Esperanza | L13: Mensaje a Instagram (e-book gratis) | M13: 335300 | N13: 11850 | O13: =IFERROR(M13/N13,"s/d") | P13: P2 · Herramienta para usar ya (decreto, ritual, técnica) | Q13: transcripciones/tiktok-2025-04-11-cuidado-con-este-video-porque-esta.md
... A79: 78 | B79: Facebook | C79: PsicoespacioVe | D79: s/d | E79: https://www.facebook.com/reel/2720591191671210/ | F79: Mañana empezamos, mi gente bella: 4 clases que te van a abrir los ojos… | G79: Anuncio | H79: Patrones repetidos | I79: Cara a cámara corto | J79: 28 s | K79: Urgencia | L79: Inscríbete (WhatsApp / link en perfil) | M79: 1700 | N79: 2375 | O79: =IFERROR(M79/N79,"s/d") | P79: P8 · Anuncio directo de evento o producto | Q79: transcripciones/facebook-cuatro-clases-gratuitas-manana-empezamos.md
A80: 79 | B80: Facebook | C80: PsicoespacioVe | D80: s/d | E80: https://www.facebook.com/reel/1897028914817172/ | F80: Acabamos de terminar la primera clase de Reprográmate… | G80: Anuncio | H80: Patrones repetidos | I80: Cara a cámara corto | J80: 44 s | K80: Urgencia | L80: Comenta CLASE (repetición) | M80: s/d | N80: 2375 | O80: =IFERROR(M80/N80,"s/d") | P80: P8 · Anuncio directo de evento o producto | Q80: transcripciones/facebook-terminamos-la-primera-clase-reprogramate.md
A82: Fuentes y supuestos:
A83: Vistas: de cada transcripción (Apify / vidIQ). En Facebook son las que muestra el título del reel (ej. "46K").
A84: Mediana de la cuenta: @mabradiante = 11,850 (mediana de 40 TikToks); @manifestadoras = 674,000 (mediana de 40 TikToks); @soylizadebri = 1,500,000 (mediana de 40 TikToks); @transformacion_acelerada = 295,900 (mediana de 40 TikToks); @danielacorreaup = 4,072 (mediana de 36 reels); @quantumquip = 4,530 (mediana de 14 reels); PsicoespacioVe = 2,375 (mediana de 27 posts con vistas). Sale de fuentes/*.json (recolección del 2026-10-06).
A85: Verde = más de 1.5x (le fue mucho mejor de lo normal para esa cuenta). Rojo = menos de 0.7x. Morado = tus propios videos.
A86: OJO: transcribimos sobre todo los videos MÁS vistos de cada cuenta, así que casi todo sale arriba de 1.5x. Sirve para ver qué tienen en común los virales; no para decir qué fracasa.
A87: Hook, tipo, tema, formato, emoción, CTA y patrón: clasificación de NICA leyendo cada transcripción. Donde no hay voz, el hook sale del caption y se marca "(caption)" o "(texto en pantalla)".

Sheet Patrones de viralidad
A1: PATRÓN | B1: Piezas | C1: Rendimiento típico (mediana) | D1: Arriba de 1.5x | E1: Abajo de 0.7x | F1: Ejemplo real
A2: P2 · Herramienta para usar ya (decreto, ritual, técnica) | B2: =COUNTIF(Competencia!$P$2:$P$80,A2) | C2: 26 | D2: =COUNTIFS(Competencia!$P$2:$P$80,A2,Competencia!$O$2:$O$80,">1.5") | E2: =COUNTIFS(Competencia!$P$2:$P$80,A2,Competencia!$O$2:$O$80,"<0.7") | F2: @mabradiante: "Di esto en tu casa y mira cómo todo comienza a cambiar." (186x)
A3: P5 · Lista o espejo de señales | B3: =COUNTIF(Competencia!$P$2:$P$80,A3) | C3: 8.9 | D3: =COUNTIFS(Competencia!$P$2:$P$80,A3,Competencia!$O$2:$O$80,">1.5") | E3: =COUNTIFS(Competencia!$P$2:$P$80,A3,Competencia!$O$2:$O$80,"<0.7") | F3: @danielacorreaup: "Odian los ruidos fuertes, pero pueden escuchar la misma canción durante cinco horas." (532x)
A4: P7 · Autoridad: estudio, famoso o cita | B4: =COUNTIF(Competencia!$P$2:$P$80,A4) | C4: 7.6 | D4: =COUNTIFS(Competencia!$P$2:$P$80,A4,Competencia!$O$2:$O$80,">1.5") | E4: =COUNTIFS(Competencia!$P$2:$P$80,A4,Competencia!$O$2:$O$80,"<0.7") | F4: @danielacorreaup: "Sabrina Carpenter es el ejemplo perfecto de cómo funciona la manifestación." (35x)
A5: P9 · Texto en pantalla + música (sin voz) | B5: =COUNTIF(Competencia!$P$2:$P$80,A5) | C5: 5.4 | D5: =COUNTIFS(Competencia!$P$2:$P$80,A5,Competencia!$O$2:$O$80,">1.5") | E5: =COUNTIFS(Competencia!$P$2:$P$80,A5,Competencia!$O$2:$O$80,"<0.7") | F5: @danielacorreaup: "(texto en pantalla) La física ya lo confirmó: lo que no puedes ver es lo que construye tod" (136x)
A6: P4 · Reacción a video ajeno de dolor o polémica | B6: =COUNTIF(Competencia!$P$2:$P$80,A6) | C6: 3.1 | D6: =COUNTIFS(Competencia!$P$2:$P$80,A6,Competencia!$O$2:$O$80,">1.5") | E6: =COUNTIFS(Competencia!$P$2:$P$80,A6,Competencia!$O$2:$O$80,"<0.7") | F6: @transformacion_acelerada: "Te lo digo crudo y sin rodeos." (3x)
A7: P1 · Romper creencia + nombre propio al problema | B7: =COUNTIF(Competencia!$P$2:$P$80,A7) | C7: 2.7 | D7: =COUNTIFS(Competencia!$P$2:$P$80,A7,Competencia!$O$2:$O$80,">1.5") | E7: =COUNTIFS(Competencia!$P$2:$P$80,A7,Competencia!$O$2:$O$80,"<0.7") | F7: @danielacorreaup: "Las personas con TDAH no tienen un déficit de atención, tienen un exceso de atención para " (614x)
A8: P3 · Dolor en sus palabras + explicación | B8: =COUNTIF(Competencia!$P$2:$P$80,A8) | C8: 2.3 | D8: =COUNTIFS(Competencia!$P$2:$P$80,A8,Competencia!$O$2:$O$80,">1.5") | E8: =COUNTIFS(Competencia!$P$2:$P$80,A8,Competencia!$O$2:$O$80,"<0.7") | F8: @danielacorreaup: "¿Cómo sabes si realmente tienes TDAH o simplemente estás distraído?" (11x)
A9: P6 · Historia o metáfora | B9: =COUNTIF(Competencia!$P$2:$P$80,A9) | C9: 1.8 | D9: =COUNTIFS(Competencia!$P$2:$P$80,A9,Competencia!$O$2:$O$80,">1.5") | E9: =COUNTIFS(Competencia!$P$2:$P$80,A9,Competencia!$O$2:$O$80,"<0.7") | F9: PsicoespacioVe: "Los bonsáis no simplemente son árboles que nacieron enanos." (14x)
A10: P8 · Anuncio directo de evento o producto | B10: =COUNTIF(Competencia!$P$2:$P$80,A10) | C10: 1.1 | D10: =COUNTIFS(Competencia!$P$2:$P$80,A10,Competencia!$O$2:$O$80,">1.5") | E10: =COUNTIFS(Competencia!$P$2:$P$80,A10,Competencia!$O$2:$O$80,"<0.7") | F10: PsicoespacioVe: "Les voy a dar un regalo… hay un programa gratuito…" (6x)
A12: La mediana la calculé con las vistas de la pestaña Competencia (es un valor fijo; si agregas filas, se recalcula en la rutina semanal).
A14: QUÉ FUNCIONA (piezas arriba de 1.5x)
A15: • Herramienta para usar ya (P2): 8 de 8 piezas arriba de 1.5x, rendimiento típico 26x. Aquí están tus 4 videos más vistos ("Di esto en tu casa…", "Cuidado con este video…").
A16: • Lista o espejo de señales (P5): 6 de 6 arriba, 8.9x. Ej.: "Odian los ruidos fuertes, pero…" (2.2M en Instagram).
A17: • Autoridad: estudio, famoso o cita (P7): 6 de 7 arriba, 7.6x. Ej.: Sabrina Carpenter, Lady Gaga, Harvard, Carl Jung.
A18: • Relaciones es el tema con más piezas virales (16) y las vistas más altas en TikTok (de 1 a 7.2 millones).
A19: • TDAH / neurodivergencia: 10 piezas, rendimiento típico 13x (cuenta @danielacorreaup). Tú tienes TDAH: es tu historia.
A21: QUÉ NO FUNCIONA (piezas abajo de 0.7x)
A22: • Casi no hay datos: transcribimos los videos más vistos, así que ninguna pieza quedó abajo de 0.7x. Lo más bajo fue:
A23: • Anuncio directo de evento o producto (P8): rendimiento típico 1.1x, el más bajo de todos. Ej.: "Mañana empezamos: 4 clases…" (0.7x).
A24: • Historias personales largas (P6): 1.8x. Funcionan, pero menos que la herramienta o la lista.
A25: • Piezas que piden "comenta para el link": 2.4x contra 4.7x de las que no venden. Vender recorta alcance: por eso solo 1 de 3 piezas al día vende.
... A40: • 3. RELACIONES es el tema con más virales del nicho y TDAH rinde 13x: los dos son tu terreno (Querido Ex y tu historia con TDAH).
